import com.arrownock.im.callback.IAnIMPushNotificationSettingsCallback;
import java.util.List;

final class ak
  implements Runnable
{
  ak(f paramf, int paramInt, String paramString, boolean paramBoolean, List paramList, IAnIMPushNotificationSettingsCallback paramIAnIMPushNotificationSettingsCallback) {}
  
  /* Error */
  public final void run()
  {
    // Byte code:
    //   0: aconst_null
    //   1: astore 4
    //   3: new 38	java/lang/StringBuffer
    //   6: astore_2
    //   7: aload_2
    //   8: invokespecial 39	java/lang/StringBuffer:<init>	()V
    //   11: aload_2
    //   12: aload_0
    //   13: getfield 17	ak:jdField_a_of_type_F	Lf;
    //   16: aload_0
    //   17: getfield 17	ak:jdField_a_of_type_F	Lf;
    //   20: invokestatic 44	f:a	(Lf;)Landroid/content/Context;
    //   23: invokestatic 47	f:a	(Lf;Landroid/content/Context;)Ljava/lang/String;
    //   26: invokevirtual 51	java/lang/StringBuffer:append	(Ljava/lang/String;)Ljava/lang/StringBuffer;
    //   29: pop
    //   30: new 53	java/lang/StringBuilder
    //   33: astore_3
    //   34: aload_3
    //   35: ldc 55
    //   37: invokespecial 58	java/lang/StringBuilder:<init>	(Ljava/lang/String;)V
    //   40: aload_2
    //   41: aload_3
    //   42: aload_0
    //   43: getfield 17	ak:jdField_a_of_type_F	Lf;
    //   46: invokestatic 62	f:b	(Lf;)Ljava/lang/String;
    //   49: invokevirtual 68	java/lang/String:trim	()Ljava/lang/String;
    //   52: invokevirtual 71	java/lang/StringBuilder:append	(Ljava/lang/String;)Ljava/lang/StringBuilder;
    //   55: invokevirtual 74	java/lang/StringBuilder:toString	()Ljava/lang/String;
    //   58: invokevirtual 51	java/lang/StringBuffer:append	(Ljava/lang/String;)Ljava/lang/StringBuffer;
    //   61: pop
    //   62: aload_0
    //   63: getfield 17	ak:jdField_a_of_type_F	Lf;
    //   66: invokestatic 77	f:a	(Lf;)Z
    //   69: ifeq +595 -> 664
    //   72: new 79	java/net/URL
    //   75: astore 5
    //   77: new 53	java/lang/StringBuilder
    //   80: astore_3
    //   81: aload_3
    //   82: ldc 81
    //   84: invokespecial 58	java/lang/StringBuilder:<init>	(Ljava/lang/String;)V
    //   87: aload 5
    //   89: aload_3
    //   90: aload_2
    //   91: invokevirtual 82	java/lang/StringBuffer:toString	()Ljava/lang/String;
    //   94: invokevirtual 71	java/lang/StringBuilder:append	(Ljava/lang/String;)Ljava/lang/StringBuilder;
    //   97: invokevirtual 74	java/lang/StringBuilder:toString	()Ljava/lang/String;
    //   100: invokespecial 83	java/net/URL:<init>	(Ljava/lang/String;)V
    //   103: aload 5
    //   105: invokevirtual 87	java/net/URL:openConnection	()Ljava/net/URLConnection;
    //   108: checkcast 89	javax/net/ssl/HttpsURLConnection
    //   111: astore_2
    //   112: aload_2
    //   113: checkcast 89	javax/net/ssl/HttpsURLConnection
    //   116: invokestatic 92	f:a	()Ljavax/net/ssl/HostnameVerifier;
    //   119: invokevirtual 96	javax/net/ssl/HttpsURLConnection:setHostnameVerifier	(Ljavax/net/ssl/HostnameVerifier;)V
    //   122: aload_2
    //   123: checkcast 89	javax/net/ssl/HttpsURLConnection
    //   126: astore_3
    //   127: aload_0
    //   128: getfield 17	ak:jdField_a_of_type_F	Lf;
    //   131: astore 5
    //   133: invokestatic 99	f:c	()Ljava/lang/String;
    //   136: astore 5
    //   138: aload_0
    //   139: getfield 17	ak:jdField_a_of_type_F	Lf;
    //   142: astore 6
    //   144: invokestatic 102	f:d	()Ljava/lang/String;
    //   147: astore 7
    //   149: aload_0
    //   150: getfield 17	ak:jdField_a_of_type_F	Lf;
    //   153: astore 6
    //   155: aload_3
    //   156: aload 5
    //   158: aload 7
    //   160: invokestatic 105	f:e	()Ljava/lang/String;
    //   163: ldc 107
    //   165: ldc 109
    //   167: invokestatic 114	at:a	(Ljava/lang/String;Ljava/lang/String;Ljava/lang/String;Ljava/lang/String;Ljava/lang/String;)Ljavax/net/ssl/SSLSocketFactory;
    //   170: invokevirtual 118	javax/net/ssl/HttpsURLConnection:setSSLSocketFactory	(Ljavax/net/ssl/SSLSocketFactory;)V
    //   173: aload_2
    //   174: astore_3
    //   175: aload_2
    //   176: ldc 120
    //   178: invokevirtual 125	java/net/HttpURLConnection:setRequestMethod	(Ljava/lang/String;)V
    //   181: aload_2
    //   182: astore_3
    //   183: aload_2
    //   184: iconst_1
    //   185: invokevirtual 129	java/net/HttpURLConnection:setDoInput	(Z)V
    //   188: aload_2
    //   189: astore_3
    //   190: aload_2
    //   191: iconst_1
    //   192: invokevirtual 132	java/net/HttpURLConnection:setDoOutput	(Z)V
    //   195: aload_2
    //   196: astore_3
    //   197: new 134	java/text/SimpleDateFormat
    //   200: astore 5
    //   202: aload_2
    //   203: astore_3
    //   204: aload 5
    //   206: ldc -120
    //   208: getstatic 142	java/util/Locale:US	Ljava/util/Locale;
    //   211: invokespecial 145	java/text/SimpleDateFormat:<init>	(Ljava/lang/String;Ljava/util/Locale;)V
    //   214: aload_2
    //   215: astore_3
    //   216: new 147	java/util/Date
    //   219: astore 6
    //   221: aload_2
    //   222: astore_3
    //   223: aload 6
    //   225: invokespecial 148	java/util/Date:<init>	()V
    //   228: aload_2
    //   229: astore_3
    //   230: aload 5
    //   232: aload 6
    //   234: invokevirtual 152	java/text/SimpleDateFormat:format	(Ljava/util/Date;)Ljava/lang/String;
    //   237: astore 6
    //   239: aload_2
    //   240: astore_3
    //   241: new 154	java/util/ArrayList
    //   244: astore 5
    //   246: aload_2
    //   247: astore_3
    //   248: aload 5
    //   250: invokespecial 155	java/util/ArrayList:<init>	()V
    //   253: aload_2
    //   254: astore_3
    //   255: new 157	org/apache/http/message/BasicNameValuePair
    //   258: astore 7
    //   260: aload_2
    //   261: astore_3
    //   262: aload 7
    //   264: ldc -97
    //   266: aload_0
    //   267: getfield 19	ak:jdField_a_of_type_Int	I
    //   270: invokestatic 163	java/lang/String:valueOf	(I)Ljava/lang/String;
    //   273: invokespecial 166	org/apache/http/message/BasicNameValuePair:<init>	(Ljava/lang/String;Ljava/lang/String;)V
    //   276: aload_2
    //   277: astore_3
    //   278: aload 5
    //   280: aload 7
    //   282: invokeinterface 172 2 0
    //   287: pop
    //   288: aload_2
    //   289: astore_3
    //   290: new 157	org/apache/http/message/BasicNameValuePair
    //   293: astore 7
    //   295: aload_2
    //   296: astore_3
    //   297: aload 7
    //   299: ldc -82
    //   301: aload_0
    //   302: getfield 21	ak:jdField_a_of_type_JavaLangString	Ljava/lang/String;
    //   305: invokespecial 166	org/apache/http/message/BasicNameValuePair:<init>	(Ljava/lang/String;Ljava/lang/String;)V
    //   308: aload_2
    //   309: astore_3
    //   310: aload 5
    //   312: aload 7
    //   314: invokeinterface 172 2 0
    //   319: pop
    //   320: aload_2
    //   321: astore_3
    //   322: new 157	org/apache/http/message/BasicNameValuePair
    //   325: astore 7
    //   327: aload_2
    //   328: astore_3
    //   329: aload 7
    //   331: ldc -80
    //   333: aload 6
    //   335: invokespecial 166	org/apache/http/message/BasicNameValuePair:<init>	(Ljava/lang/String;Ljava/lang/String;)V
    //   338: aload_2
    //   339: astore_3
    //   340: aload 5
    //   342: aload 7
    //   344: invokeinterface 172 2 0
    //   349: pop
    //   350: aload_2
    //   351: astore_3
    //   352: new 157	org/apache/http/message/BasicNameValuePair
    //   355: astore 7
    //   357: aload_2
    //   358: astore_3
    //   359: aload 7
    //   361: ldc -78
    //   363: ldc -76
    //   365: invokespecial 166	org/apache/http/message/BasicNameValuePair:<init>	(Ljava/lang/String;Ljava/lang/String;)V
    //   368: aload_2
    //   369: astore_3
    //   370: aload 5
    //   372: aload 7
    //   374: invokeinterface 172 2 0
    //   379: pop
    //   380: aload_2
    //   381: astore_3
    //   382: aload_0
    //   383: getfield 19	ak:jdField_a_of_type_Int	I
    //   386: tableswitch	default:+38->424, 1:+322->708, 2:+322->708, 3:+322->708, 4:+447->833, 5:+447->833, 6:+322->708
    //   424: aload_2
    //   425: astore_3
    //   426: new 182	javax/crypto/spec/SecretKeySpec
    //   429: astore 6
    //   431: aload_2
    //   432: astore_3
    //   433: aload 6
    //   435: ldc -72
    //   437: invokevirtual 188	java/lang/String:getBytes	()[B
    //   440: ldc -66
    //   442: invokespecial 193	javax/crypto/spec/SecretKeySpec:<init>	([BLjava/lang/String;)V
    //   445: aload_2
    //   446: astore_3
    //   447: ldc -66
    //   449: invokestatic 199	javax/crypto/Mac:getInstance	(Ljava/lang/String;)Ljavax/crypto/Mac;
    //   452: astore 7
    //   454: aload_2
    //   455: astore_3
    //   456: aload 7
    //   458: aload 6
    //   460: invokevirtual 203	javax/crypto/Mac:init	(Ljava/security/Key;)V
    //   463: aload_2
    //   464: astore_3
    //   465: aload 7
    //   467: aload 4
    //   469: invokevirtual 188	java/lang/String:getBytes	()[B
    //   472: invokevirtual 207	javax/crypto/Mac:doFinal	([B)[B
    //   475: iconst_2
    //   476: invokestatic 213	android/util/Base64:encodeToString	([BI)Ljava/lang/String;
    //   479: astore 4
    //   481: aload_2
    //   482: astore_3
    //   483: new 157	org/apache/http/message/BasicNameValuePair
    //   486: astore 6
    //   488: aload_2
    //   489: astore_3
    //   490: aload 6
    //   492: ldc -41
    //   494: aload 4
    //   496: invokespecial 166	org/apache/http/message/BasicNameValuePair:<init>	(Ljava/lang/String;Ljava/lang/String;)V
    //   499: aload_2
    //   500: astore_3
    //   501: aload 5
    //   503: aload 6
    //   505: invokeinterface 172 2 0
    //   510: pop
    //   511: aload_2
    //   512: astore_3
    //   513: aload_2
    //   514: invokevirtual 219	java/net/HttpURLConnection:getOutputStream	()Ljava/io/OutputStream;
    //   517: astore 4
    //   519: aload_2
    //   520: astore_3
    //   521: new 221	java/io/BufferedWriter
    //   524: astore 6
    //   526: aload_2
    //   527: astore_3
    //   528: new 223	java/io/OutputStreamWriter
    //   531: astore 7
    //   533: aload_2
    //   534: astore_3
    //   535: aload 7
    //   537: aload 4
    //   539: ldc -31
    //   541: invokespecial 228	java/io/OutputStreamWriter:<init>	(Ljava/io/OutputStream;Ljava/lang/String;)V
    //   544: aload_2
    //   545: astore_3
    //   546: aload 6
    //   548: aload 7
    //   550: invokespecial 231	java/io/BufferedWriter:<init>	(Ljava/io/Writer;)V
    //   553: aload_2
    //   554: astore_3
    //   555: aload_0
    //   556: getfield 17	ak:jdField_a_of_type_F	Lf;
    //   559: astore 7
    //   561: aload_2
    //   562: astore_3
    //   563: aload 6
    //   565: aload 5
    //   567: invokestatic 234	f:a	(Ljava/util/List;)Ljava/lang/String;
    //   570: invokevirtual 237	java/io/BufferedWriter:write	(Ljava/lang/String;)V
    //   573: aload_2
    //   574: astore_3
    //   575: aload 6
    //   577: invokevirtual 240	java/io/BufferedWriter:close	()V
    //   580: aload_2
    //   581: astore_3
    //   582: aload 4
    //   584: invokevirtual 243	java/io/OutputStream:close	()V
    //   587: aload_2
    //   588: astore_3
    //   589: aload_2
    //   590: invokevirtual 247	java/net/HttpURLConnection:getResponseCode	()I
    //   593: istore_1
    //   594: iload_1
    //   595: sipush 200
    //   598: if_icmpne +539 -> 1137
    //   601: aload_2
    //   602: astore_3
    //   603: new 249	java/io/BufferedInputStream
    //   606: astore 4
    //   608: aload_2
    //   609: astore_3
    //   610: aload 4
    //   612: aload_2
    //   613: invokevirtual 253	java/net/HttpURLConnection:getInputStream	()Ljava/io/InputStream;
    //   616: invokespecial 256	java/io/BufferedInputStream:<init>	(Ljava/io/InputStream;)V
    //   619: aload_2
    //   620: astore_3
    //   621: aload_0
    //   622: getfield 17	ak:jdField_a_of_type_F	Lf;
    //   625: astore 5
    //   627: aload_2
    //   628: astore_3
    //   629: aload 4
    //   631: invokestatic 259	f:a	(Ljava/io/InputStream;)Ljava/lang/String;
    //   634: pop
    //   635: aload_2
    //   636: astore_3
    //   637: aload_0
    //   638: getfield 27	ak:jdField_a_of_type_ComArrownockImCallbackIAnIMPushNotificationSettingsCallback	Lcom/arrownock/im/callback/IAnIMPushNotificationSettingsCallback;
    //   641: ifnull +14 -> 655
    //   644: aload_2
    //   645: astore_3
    //   646: aload_0
    //   647: getfield 27	ak:jdField_a_of_type_ComArrownockImCallbackIAnIMPushNotificationSettingsCallback	Lcom/arrownock/im/callback/IAnIMPushNotificationSettingsCallback;
    //   650: invokeinterface 264 1 0
    //   655: aload_2
    //   656: ifnull +7 -> 663
    //   659: aload_2
    //   660: invokevirtual 267	java/net/HttpURLConnection:disconnect	()V
    //   663: return
    //   664: new 79	java/net/URL
    //   667: astore 5
    //   669: new 53	java/lang/StringBuilder
    //   672: astore_3
    //   673: aload_3
    //   674: ldc_w 269
    //   677: invokespecial 58	java/lang/StringBuilder:<init>	(Ljava/lang/String;)V
    //   680: aload 5
    //   682: aload_3
    //   683: aload_2
    //   684: invokevirtual 82	java/lang/StringBuffer:toString	()Ljava/lang/String;
    //   687: invokevirtual 71	java/lang/StringBuilder:append	(Ljava/lang/String;)Ljava/lang/StringBuilder;
    //   690: invokevirtual 74	java/lang/StringBuilder:toString	()Ljava/lang/String;
    //   693: invokespecial 83	java/net/URL:<init>	(Ljava/lang/String;)V
    //   696: aload 5
    //   698: invokevirtual 87	java/net/URL:openConnection	()Ljava/net/URLConnection;
    //   701: checkcast 122	java/net/HttpURLConnection
    //   704: astore_2
    //   705: goto -532 -> 173
    //   708: aload_2
    //   709: astore_3
    //   710: new 157	org/apache/http/message/BasicNameValuePair
    //   713: astore 4
    //   715: aload_2
    //   716: astore_3
    //   717: aload 4
    //   719: ldc_w 271
    //   722: aload_0
    //   723: getfield 23	ak:jdField_a_of_type_Boolean	Z
    //   726: invokestatic 274	java/lang/String:valueOf	(Z)Ljava/lang/String;
    //   729: invokespecial 166	org/apache/http/message/BasicNameValuePair:<init>	(Ljava/lang/String;Ljava/lang/String;)V
    //   732: aload_2
    //   733: astore_3
    //   734: aload 5
    //   736: aload 4
    //   738: invokeinterface 172 2 0
    //   743: pop
    //   744: aload_2
    //   745: astore_3
    //   746: new 53	java/lang/StringBuilder
    //   749: astore 4
    //   751: aload_2
    //   752: astore_3
    //   753: aload 4
    //   755: ldc_w 276
    //   758: invokespecial 58	java/lang/StringBuilder:<init>	(Ljava/lang/String;)V
    //   761: aload_2
    //   762: astore_3
    //   763: aload 4
    //   765: aload_0
    //   766: getfield 21	ak:jdField_a_of_type_JavaLangString	Ljava/lang/String;
    //   769: invokevirtual 71	java/lang/StringBuilder:append	(Ljava/lang/String;)Ljava/lang/StringBuilder;
    //   772: ldc_w 278
    //   775: invokevirtual 71	java/lang/StringBuilder:append	(Ljava/lang/String;)Ljava/lang/StringBuilder;
    //   778: aload 6
    //   780: invokevirtual 71	java/lang/StringBuilder:append	(Ljava/lang/String;)Ljava/lang/StringBuilder;
    //   783: ldc_w 280
    //   786: invokevirtual 71	java/lang/StringBuilder:append	(Ljava/lang/String;)Ljava/lang/StringBuilder;
    //   789: aload_0
    //   790: getfield 17	ak:jdField_a_of_type_F	Lf;
    //   793: invokestatic 62	f:b	(Lf;)Ljava/lang/String;
    //   796: invokevirtual 71	java/lang/StringBuilder:append	(Ljava/lang/String;)Ljava/lang/StringBuilder;
    //   799: ldc_w 282
    //   802: invokevirtual 71	java/lang/StringBuilder:append	(Ljava/lang/String;)Ljava/lang/StringBuilder;
    //   805: aload_0
    //   806: getfield 19	ak:jdField_a_of_type_Int	I
    //   809: invokevirtual 285	java/lang/StringBuilder:append	(I)Ljava/lang/StringBuilder;
    //   812: ldc_w 287
    //   815: invokevirtual 71	java/lang/StringBuilder:append	(Ljava/lang/String;)Ljava/lang/StringBuilder;
    //   818: aload_0
    //   819: getfield 23	ak:jdField_a_of_type_Boolean	Z
    //   822: invokevirtual 290	java/lang/StringBuilder:append	(Z)Ljava/lang/StringBuilder;
    //   825: invokevirtual 74	java/lang/StringBuilder:toString	()Ljava/lang/String;
    //   828: astore 4
    //   830: goto -406 -> 424
    //   833: aload_2
    //   834: astore_3
    //   835: new 38	java/lang/StringBuffer
    //   838: astore 7
    //   840: aload_2
    //   841: astore_3
    //   842: aload 7
    //   844: invokespecial 39	java/lang/StringBuffer:<init>	()V
    //   847: aload_2
    //   848: astore_3
    //   849: aload_0
    //   850: getfield 25	ak:jdField_a_of_type_JavaUtilList	Ljava/util/List;
    //   853: invokeinterface 294 1 0
    //   858: astore 4
    //   860: aload_2
    //   861: astore_3
    //   862: aload 4
    //   864: invokeinterface 300 1 0
    //   869: ifeq +78 -> 947
    //   872: aload_2
    //   873: astore_3
    //   874: aload 7
    //   876: aload 4
    //   878: invokeinterface 304 1 0
    //   883: checkcast 64	java/lang/String
    //   886: invokevirtual 51	java/lang/StringBuffer:append	(Ljava/lang/String;)Ljava/lang/StringBuffer;
    //   889: ldc_w 306
    //   892: invokevirtual 51	java/lang/StringBuffer:append	(Ljava/lang/String;)Ljava/lang/StringBuffer;
    //   895: pop
    //   896: goto -36 -> 860
    //   899: astore 4
    //   901: aload_2
    //   902: astore_3
    //   903: aload 4
    //   905: instanceof 308
    //   908: ifeq +351 -> 1259
    //   911: aload_2
    //   912: astore_3
    //   913: aload_0
    //   914: getfield 27	ak:jdField_a_of_type_ComArrownockImCallbackIAnIMPushNotificationSettingsCallback	Lcom/arrownock/im/callback/IAnIMPushNotificationSettingsCallback;
    //   917: ifnull +19 -> 936
    //   920: aload_2
    //   921: astore_3
    //   922: aload_0
    //   923: getfield 27	ak:jdField_a_of_type_ComArrownockImCallbackIAnIMPushNotificationSettingsCallback	Lcom/arrownock/im/callback/IAnIMPushNotificationSettingsCallback;
    //   926: aload 4
    //   928: checkcast 308	com/arrownock/exception/ArrownockException
    //   931: invokeinterface 312 2 0
    //   936: aload_2
    //   937: ifnull -274 -> 663
    //   940: aload_2
    //   941: invokevirtual 267	java/net/HttpURLConnection:disconnect	()V
    //   944: goto -281 -> 663
    //   947: ldc 107
    //   949: astore 4
    //   951: aload_2
    //   952: astore_3
    //   953: aload 7
    //   955: invokevirtual 315	java/lang/StringBuffer:length	()I
    //   958: iconst_1
    //   959: if_icmple +20 -> 979
    //   962: aload_2
    //   963: astore_3
    //   964: aload 7
    //   966: iconst_0
    //   967: aload 7
    //   969: invokevirtual 315	java/lang/StringBuffer:length	()I
    //   972: iconst_1
    //   973: isub
    //   974: invokevirtual 319	java/lang/StringBuffer:substring	(II)Ljava/lang/String;
    //   977: astore 4
    //   979: aload_2
    //   980: astore_3
    //   981: new 157	org/apache/http/message/BasicNameValuePair
    //   984: astore 7
    //   986: aload_2
    //   987: astore_3
    //   988: aload 7
    //   990: ldc_w 271
    //   993: aload 4
    //   995: invokespecial 166	org/apache/http/message/BasicNameValuePair:<init>	(Ljava/lang/String;Ljava/lang/String;)V
    //   998: aload_2
    //   999: astore_3
    //   1000: aload 5
    //   1002: aload 7
    //   1004: invokeinterface 172 2 0
    //   1009: pop
    //   1010: aload_2
    //   1011: astore_3
    //   1012: new 53	java/lang/StringBuilder
    //   1015: astore 7
    //   1017: aload_2
    //   1018: astore_3
    //   1019: aload 7
    //   1021: ldc_w 276
    //   1024: invokespecial 58	java/lang/StringBuilder:<init>	(Ljava/lang/String;)V
    //   1027: aload_2
    //   1028: astore_3
    //   1029: aload 7
    //   1031: aload_0
    //   1032: getfield 21	ak:jdField_a_of_type_JavaLangString	Ljava/lang/String;
    //   1035: invokevirtual 71	java/lang/StringBuilder:append	(Ljava/lang/String;)Ljava/lang/StringBuilder;
    //   1038: ldc_w 278
    //   1041: invokevirtual 71	java/lang/StringBuilder:append	(Ljava/lang/String;)Ljava/lang/StringBuilder;
    //   1044: aload 6
    //   1046: invokevirtual 71	java/lang/StringBuilder:append	(Ljava/lang/String;)Ljava/lang/StringBuilder;
    //   1049: ldc_w 280
    //   1052: invokevirtual 71	java/lang/StringBuilder:append	(Ljava/lang/String;)Ljava/lang/StringBuilder;
    //   1055: aload_0
    //   1056: getfield 17	ak:jdField_a_of_type_F	Lf;
    //   1059: invokestatic 62	f:b	(Lf;)Ljava/lang/String;
    //   1062: invokevirtual 71	java/lang/StringBuilder:append	(Ljava/lang/String;)Ljava/lang/StringBuilder;
    //   1065: ldc_w 282
    //   1068: invokevirtual 71	java/lang/StringBuilder:append	(Ljava/lang/String;)Ljava/lang/StringBuilder;
    //   1071: aload_0
    //   1072: getfield 19	ak:jdField_a_of_type_Int	I
    //   1075: invokevirtual 285	java/lang/StringBuilder:append	(I)Ljava/lang/StringBuilder;
    //   1078: ldc_w 287
    //   1081: invokevirtual 71	java/lang/StringBuilder:append	(Ljava/lang/String;)Ljava/lang/StringBuilder;
    //   1084: aload 4
    //   1086: invokevirtual 71	java/lang/StringBuilder:append	(Ljava/lang/String;)Ljava/lang/StringBuilder;
    //   1089: invokevirtual 74	java/lang/StringBuilder:toString	()Ljava/lang/String;
    //   1092: astore 4
    //   1094: goto -670 -> 424
    //   1097: astore 5
    //   1099: aload_2
    //   1100: astore_3
    //   1101: new 308	com/arrownock/exception/ArrownockException
    //   1104: astore 4
    //   1106: aload_2
    //   1107: astore_3
    //   1108: aload 4
    //   1110: aload 5
    //   1112: invokevirtual 322	java/lang/Exception:getMessage	()Ljava/lang/String;
    //   1115: sipush 2107
    //   1118: invokespecial 325	com/arrownock/exception/ArrownockException:<init>	(Ljava/lang/String;I)V
    //   1121: aload_2
    //   1122: astore_3
    //   1123: aload 4
    //   1125: athrow
    //   1126: astore_2
    //   1127: aload_3
    //   1128: ifnull +7 -> 1135
    //   1131: aload_3
    //   1132: invokevirtual 267	java/net/HttpURLConnection:disconnect	()V
    //   1135: aload_2
    //   1136: athrow
    //   1137: aload_2
    //   1138: astore_3
    //   1139: new 249	java/io/BufferedInputStream
    //   1142: astore 4
    //   1144: aload_2
    //   1145: astore_3
    //   1146: aload 4
    //   1148: aload_2
    //   1149: invokevirtual 328	java/net/HttpURLConnection:getErrorStream	()Ljava/io/InputStream;
    //   1152: invokespecial 256	java/io/BufferedInputStream:<init>	(Ljava/io/InputStream;)V
    //   1155: aload_2
    //   1156: astore_3
    //   1157: aload_0
    //   1158: getfield 17	ak:jdField_a_of_type_F	Lf;
    //   1161: astore 5
    //   1163: aload_2
    //   1164: astore_3
    //   1165: aload 4
    //   1167: invokestatic 259	f:a	(Ljava/io/InputStream;)Ljava/lang/String;
    //   1170: astore 4
    //   1172: aload_2
    //   1173: astore_3
    //   1174: new 330	org/json/JSONObject
    //   1177: astore 5
    //   1179: aload_2
    //   1180: astore_3
    //   1181: aload 5
    //   1183: aload 4
    //   1185: invokespecial 331	org/json/JSONObject:<init>	(Ljava/lang/String;)V
    //   1188: aload_2
    //   1189: astore_3
    //   1190: aload 5
    //   1192: ldc_w 333
    //   1195: invokevirtual 337	org/json/JSONObject:getJSONObject	(Ljava/lang/String;)Lorg/json/JSONObject;
    //   1198: astore 4
    //   1200: aload_2
    //   1201: astore_3
    //   1202: new 308	com/arrownock/exception/ArrownockException
    //   1205: astore 5
    //   1207: aload_2
    //   1208: astore_3
    //   1209: aload 5
    //   1211: aload 4
    //   1213: ldc_w 339
    //   1216: invokevirtual 343	org/json/JSONObject:getString	(Ljava/lang/String;)Ljava/lang/String;
    //   1219: sipush 2116
    //   1222: invokespecial 325	com/arrownock/exception/ArrownockException:<init>	(Ljava/lang/String;I)V
    //   1225: aload_2
    //   1226: astore_3
    //   1227: aload 5
    //   1229: athrow
    //   1230: astore 4
    //   1232: aload_2
    //   1233: astore_3
    //   1234: new 308	com/arrownock/exception/ArrownockException
    //   1237: astore 5
    //   1239: aload_2
    //   1240: astore_3
    //   1241: aload 5
    //   1243: aload 4
    //   1245: invokevirtual 344	org/json/JSONException:getMessage	()Ljava/lang/String;
    //   1248: sipush 2116
    //   1251: invokespecial 325	com/arrownock/exception/ArrownockException:<init>	(Ljava/lang/String;I)V
    //   1254: aload_2
    //   1255: astore_3
    //   1256: aload 5
    //   1258: athrow
    //   1259: aload_2
    //   1260: astore_3
    //   1261: aload_0
    //   1262: getfield 27	ak:jdField_a_of_type_ComArrownockImCallbackIAnIMPushNotificationSettingsCallback	Lcom/arrownock/im/callback/IAnIMPushNotificationSettingsCallback;
    //   1265: ifnull -329 -> 936
    //   1268: aload_2
    //   1269: astore_3
    //   1270: aload_0
    //   1271: getfield 27	ak:jdField_a_of_type_ComArrownockImCallbackIAnIMPushNotificationSettingsCallback	Lcom/arrownock/im/callback/IAnIMPushNotificationSettingsCallback;
    //   1274: astore 5
    //   1276: aload_2
    //   1277: astore_3
    //   1278: new 308	com/arrownock/exception/ArrownockException
    //   1281: astore 6
    //   1283: aload_2
    //   1284: astore_3
    //   1285: aload 6
    //   1287: aload 4
    //   1289: invokevirtual 322	java/lang/Exception:getMessage	()Ljava/lang/String;
    //   1292: sipush 2116
    //   1295: invokespecial 325	com/arrownock/exception/ArrownockException:<init>	(Ljava/lang/String;I)V
    //   1298: aload_2
    //   1299: astore_3
    //   1300: aload 5
    //   1302: aload 6
    //   1304: invokeinterface 312 2 0
    //   1309: goto -373 -> 936
    //   1312: astore_2
    //   1313: aconst_null
    //   1314: astore_3
    //   1315: goto -188 -> 1127
    //   1318: astore 4
    //   1320: aload_2
    //   1321: astore_3
    //   1322: aload 4
    //   1324: astore_2
    //   1325: goto -198 -> 1127
    //   1328: astore 4
    //   1330: aconst_null
    //   1331: astore_2
    //   1332: goto -431 -> 901
    //   1335: astore 4
    //   1337: goto -436 -> 901
    // Local variable table:
    //   start	length	slot	name	signature
    //   0	1340	0	this	ak
    //   593	6	1	i	int
    //   6	1116	2	localObject1	Object
    //   1126	173	2	localObject2	Object
    //   1312	9	2	localObject3	Object
    //   1324	8	2	localObject4	Object
    //   33	1289	3	localObject5	Object
    //   1	876	4	localObject6	Object
    //   899	28	4	localException1	Exception
    //   949	263	4	localObject7	Object
    //   1230	58	4	localJSONException	org.json.JSONException
    //   1318	5	4	localObject8	Object
    //   1328	1	4	localException2	Exception
    //   1335	1	4	localException3	Exception
    //   75	926	5	localObject9	Object
    //   1097	14	5	localException4	Exception
    //   1161	140	5	localObject10	Object
    //   142	1161	6	localObject11	Object
    //   147	883	7	localObject12	Object
    // Exception table:
    //   from	to	target	type
    //   175	181	899	java/lang/Exception
    //   183	188	899	java/lang/Exception
    //   190	195	899	java/lang/Exception
    //   197	202	899	java/lang/Exception
    //   204	214	899	java/lang/Exception
    //   216	221	899	java/lang/Exception
    //   223	228	899	java/lang/Exception
    //   230	239	899	java/lang/Exception
    //   241	246	899	java/lang/Exception
    //   248	253	899	java/lang/Exception
    //   255	260	899	java/lang/Exception
    //   262	276	899	java/lang/Exception
    //   278	288	899	java/lang/Exception
    //   290	295	899	java/lang/Exception
    //   297	308	899	java/lang/Exception
    //   310	320	899	java/lang/Exception
    //   322	327	899	java/lang/Exception
    //   329	338	899	java/lang/Exception
    //   340	350	899	java/lang/Exception
    //   352	357	899	java/lang/Exception
    //   359	368	899	java/lang/Exception
    //   370	380	899	java/lang/Exception
    //   382	424	899	java/lang/Exception
    //   513	519	899	java/lang/Exception
    //   521	526	899	java/lang/Exception
    //   528	533	899	java/lang/Exception
    //   535	544	899	java/lang/Exception
    //   546	553	899	java/lang/Exception
    //   555	561	899	java/lang/Exception
    //   563	573	899	java/lang/Exception
    //   575	580	899	java/lang/Exception
    //   582	587	899	java/lang/Exception
    //   589	594	899	java/lang/Exception
    //   603	608	899	java/lang/Exception
    //   610	619	899	java/lang/Exception
    //   621	627	899	java/lang/Exception
    //   629	635	899	java/lang/Exception
    //   637	644	899	java/lang/Exception
    //   646	655	899	java/lang/Exception
    //   710	715	899	java/lang/Exception
    //   717	732	899	java/lang/Exception
    //   734	744	899	java/lang/Exception
    //   746	751	899	java/lang/Exception
    //   753	761	899	java/lang/Exception
    //   763	830	899	java/lang/Exception
    //   835	840	899	java/lang/Exception
    //   842	847	899	java/lang/Exception
    //   849	860	899	java/lang/Exception
    //   862	872	899	java/lang/Exception
    //   874	896	899	java/lang/Exception
    //   953	962	899	java/lang/Exception
    //   964	979	899	java/lang/Exception
    //   981	986	899	java/lang/Exception
    //   988	998	899	java/lang/Exception
    //   1000	1010	899	java/lang/Exception
    //   1012	1017	899	java/lang/Exception
    //   1019	1027	899	java/lang/Exception
    //   1029	1094	899	java/lang/Exception
    //   1101	1106	899	java/lang/Exception
    //   1108	1121	899	java/lang/Exception
    //   1123	1126	899	java/lang/Exception
    //   1139	1144	899	java/lang/Exception
    //   1146	1155	899	java/lang/Exception
    //   1157	1163	899	java/lang/Exception
    //   1165	1172	899	java/lang/Exception
    //   1174	1179	899	java/lang/Exception
    //   1181	1188	899	java/lang/Exception
    //   1190	1200	899	java/lang/Exception
    //   1202	1207	899	java/lang/Exception
    //   1209	1225	899	java/lang/Exception
    //   1227	1230	899	java/lang/Exception
    //   1234	1239	899	java/lang/Exception
    //   1241	1254	899	java/lang/Exception
    //   1256	1259	899	java/lang/Exception
    //   426	431	1097	java/lang/Exception
    //   433	445	1097	java/lang/Exception
    //   447	454	1097	java/lang/Exception
    //   456	463	1097	java/lang/Exception
    //   465	481	1097	java/lang/Exception
    //   483	488	1097	java/lang/Exception
    //   490	499	1097	java/lang/Exception
    //   501	511	1097	java/lang/Exception
    //   175	181	1126	finally
    //   183	188	1126	finally
    //   190	195	1126	finally
    //   197	202	1126	finally
    //   204	214	1126	finally
    //   216	221	1126	finally
    //   223	228	1126	finally
    //   230	239	1126	finally
    //   241	246	1126	finally
    //   248	253	1126	finally
    //   255	260	1126	finally
    //   262	276	1126	finally
    //   278	288	1126	finally
    //   290	295	1126	finally
    //   297	308	1126	finally
    //   310	320	1126	finally
    //   322	327	1126	finally
    //   329	338	1126	finally
    //   340	350	1126	finally
    //   352	357	1126	finally
    //   359	368	1126	finally
    //   370	380	1126	finally
    //   382	424	1126	finally
    //   426	431	1126	finally
    //   433	445	1126	finally
    //   447	454	1126	finally
    //   456	463	1126	finally
    //   465	481	1126	finally
    //   483	488	1126	finally
    //   490	499	1126	finally
    //   501	511	1126	finally
    //   513	519	1126	finally
    //   521	526	1126	finally
    //   528	533	1126	finally
    //   535	544	1126	finally
    //   546	553	1126	finally
    //   555	561	1126	finally
    //   563	573	1126	finally
    //   575	580	1126	finally
    //   582	587	1126	finally
    //   589	594	1126	finally
    //   603	608	1126	finally
    //   610	619	1126	finally
    //   621	627	1126	finally
    //   629	635	1126	finally
    //   637	644	1126	finally
    //   646	655	1126	finally
    //   710	715	1126	finally
    //   717	732	1126	finally
    //   734	744	1126	finally
    //   746	751	1126	finally
    //   753	761	1126	finally
    //   763	830	1126	finally
    //   835	840	1126	finally
    //   842	847	1126	finally
    //   849	860	1126	finally
    //   862	872	1126	finally
    //   874	896	1126	finally
    //   903	911	1126	finally
    //   913	920	1126	finally
    //   922	936	1126	finally
    //   953	962	1126	finally
    //   964	979	1126	finally
    //   981	986	1126	finally
    //   988	998	1126	finally
    //   1000	1010	1126	finally
    //   1012	1017	1126	finally
    //   1019	1027	1126	finally
    //   1029	1094	1126	finally
    //   1101	1106	1126	finally
    //   1108	1121	1126	finally
    //   1123	1126	1126	finally
    //   1139	1144	1126	finally
    //   1146	1155	1126	finally
    //   1157	1163	1126	finally
    //   1165	1172	1126	finally
    //   1174	1179	1126	finally
    //   1181	1188	1126	finally
    //   1190	1200	1126	finally
    //   1202	1207	1126	finally
    //   1209	1225	1126	finally
    //   1227	1230	1126	finally
    //   1234	1239	1126	finally
    //   1241	1254	1126	finally
    //   1256	1259	1126	finally
    //   1261	1268	1126	finally
    //   1270	1276	1126	finally
    //   1278	1283	1126	finally
    //   1285	1298	1126	finally
    //   1300	1309	1126	finally
    //   603	608	1230	org/json/JSONException
    //   610	619	1230	org/json/JSONException
    //   621	627	1230	org/json/JSONException
    //   629	635	1230	org/json/JSONException
    //   637	644	1230	org/json/JSONException
    //   646	655	1230	org/json/JSONException
    //   1139	1144	1230	org/json/JSONException
    //   1146	1155	1230	org/json/JSONException
    //   1157	1163	1230	org/json/JSONException
    //   1165	1172	1230	org/json/JSONException
    //   1174	1179	1230	org/json/JSONException
    //   1181	1188	1230	org/json/JSONException
    //   1190	1200	1230	org/json/JSONException
    //   1202	1207	1230	org/json/JSONException
    //   1209	1225	1230	org/json/JSONException
    //   1227	1230	1230	org/json/JSONException
    //   3	112	1312	finally
    //   664	705	1312	finally
    //   112	173	1318	finally
    //   3	112	1328	java/lang/Exception
    //   664	705	1328	java/lang/Exception
    //   112	173	1335	java/lang/Exception
  }
}


/* Location:              E:\soft\ApkIDE\Worksrc\com.MobileTicket\!\ak.class
 * Java compiler version: 6 (50.0)
 * JD-Core Version:       0.7.1
 */