import com.arrownock.push.IAnPushRegistrationCallback;

final class dq
  implements Runnable
{
  dq(df paramdf, String paramString1, IAnPushRegistrationCallback paramIAnPushRegistrationCallback, String paramString2, String paramString3, String paramString4, boolean paramBoolean) {}
  
  /* Error */
  public final void run()
  {
    // Byte code:
    //   0: aconst_null
    //   1: astore 4
    //   3: aconst_null
    //   4: astore_3
    //   5: aload_0
    //   6: getfield 20	dq:jdField_a_of_type_JavaLangString	Ljava/lang/String;
    //   9: ldc 43
    //   11: invokevirtual 49	java/lang/String:equals	(Ljava/lang/Object;)Z
    //   14: ifeq +520 -> 534
    //   17: aload_0
    //   18: getfield 18	dq:jdField_a_of_type_Df	Ldf;
    //   21: invokestatic 54	df:a	(Ldf;)Z
    //   24: ifeq +475 -> 499
    //   27: aload_0
    //   28: getfield 18	dq:jdField_a_of_type_Df	Ldf;
    //   31: aload_0
    //   32: getfield 18	dq:jdField_a_of_type_Df	Ldf;
    //   35: invokestatic 57	df:a	(Ldf;)Landroid/content/Context;
    //   38: invokevirtual 60	df:a	(Landroid/content/Context;)Ljava/lang/String;
    //   41: astore_3
    //   42: aload_3
    //   43: invokevirtual 64	java/lang/String:isEmpty	()Z
    //   46: ifeq +268 -> 314
    //   49: aload_0
    //   50: getfield 18	dq:jdField_a_of_type_Df	Ldf;
    //   53: invokestatic 57	df:a	(Ldf;)Landroid/content/Context;
    //   56: invokestatic 70	com/google/android/gms/gcm/GoogleCloudMessaging:getInstance	(Landroid/content/Context;)Lcom/google/android/gms/gcm/GoogleCloudMessaging;
    //   59: astore 4
    //   61: aload_3
    //   62: astore_2
    //   63: aload 4
    //   65: invokevirtual 73	com/google/android/gms/gcm/GoogleCloudMessaging:unregister	()V
    //   68: aload_3
    //   69: astore_2
    //   70: aload 4
    //   72: iconst_1
    //   73: anewarray 45	java/lang/String
    //   76: dup
    //   77: iconst_0
    //   78: aload_0
    //   79: getfield 18	dq:jdField_a_of_type_Df	Ldf;
    //   82: invokestatic 57	df:a	(Ldf;)Landroid/content/Context;
    //   85: invokestatic 78	com/arrownock/push/AnPush:getInstance	(Landroid/content/Context;)Lcom/arrownock/push/AnPush;
    //   88: invokevirtual 82	com/arrownock/push/AnPush:getSenderId	()Ljava/lang/String;
    //   91: aastore
    //   92: invokevirtual 86	com/google/android/gms/gcm/GoogleCloudMessaging:register	([Ljava/lang/String;)Ljava/lang/String;
    //   95: astore_3
    //   96: aload_3
    //   97: astore_2
    //   98: new 88	java/lang/StringBuilder
    //   101: astore 4
    //   103: aload_3
    //   104: astore_2
    //   105: aload 4
    //   107: ldc 90
    //   109: invokespecial 93	java/lang/StringBuilder:<init>	(Ljava/lang/String;)V
    //   112: aload_3
    //   113: astore_2
    //   114: ldc 95
    //   116: aload 4
    //   118: aload_3
    //   119: invokevirtual 99	java/lang/StringBuilder:append	(Ljava/lang/String;)Ljava/lang/StringBuilder;
    //   122: invokevirtual 102	java/lang/StringBuilder:toString	()Ljava/lang/String;
    //   125: invokestatic 107	android/util/Log:d	(Ljava/lang/String;Ljava/lang/String;)I
    //   128: pop
    //   129: aload_3
    //   130: astore_2
    //   131: aload_0
    //   132: getfield 18	dq:jdField_a_of_type_Df	Ldf;
    //   135: aload_0
    //   136: getfield 18	dq:jdField_a_of_type_Df	Ldf;
    //   139: invokestatic 57	df:a	(Ldf;)Landroid/content/Context;
    //   142: aload_3
    //   143: invokestatic 110	df:a	(Ldf;Landroid/content/Context;Ljava/lang/String;)V
    //   146: aload_3
    //   147: astore_2
    //   148: aload_0
    //   149: getfield 18	dq:jdField_a_of_type_Df	Ldf;
    //   152: ldc 112
    //   154: aconst_null
    //   155: invokevirtual 115	df:a	(Ljava/lang/String;Ljava/lang/String;)Ljava/lang/String;
    //   158: astore 4
    //   160: aload_0
    //   161: getfield 24	dq:b	Ljava/lang/String;
    //   164: ifnonnull +327 -> 491
    //   167: aload 4
    //   169: astore_3
    //   170: aload 4
    //   172: ifnonnull +26 -> 198
    //   175: aload_0
    //   176: getfield 18	dq:jdField_a_of_type_Df	Ldf;
    //   179: aload_0
    //   180: getfield 18	dq:jdField_a_of_type_Df	Ldf;
    //   183: invokestatic 57	df:a	(Ldf;)Landroid/content/Context;
    //   186: aload_0
    //   187: getfield 26	dq:c	Ljava/lang/String;
    //   190: invokevirtual 118	df:a	(Landroid/content/Context;Ljava/lang/String;)Ljava/lang/String;
    //   193: astore_3
    //   194: aload_3
    //   195: ifnull +848 -> 1043
    //   198: aload_0
    //   199: getfield 18	dq:jdField_a_of_type_Df	Ldf;
    //   202: aload_0
    //   203: getfield 26	dq:c	Ljava/lang/String;
    //   206: aload_2
    //   207: aload_0
    //   208: getfield 28	dq:d	Ljava/lang/String;
    //   211: aload_0
    //   212: getfield 30	dq:jdField_a_of_type_Boolean	Z
    //   215: aload_0
    //   216: getfield 20	dq:jdField_a_of_type_JavaLangString	Ljava/lang/String;
    //   219: aload_3
    //   220: invokevirtual 121	df:a	(Ljava/lang/String;Ljava/lang/String;Ljava/lang/String;ZLjava/lang/String;Ljava/lang/String;)Ljava/lang/String;
    //   223: astore_2
    //   224: aload_0
    //   225: getfield 18	dq:jdField_a_of_type_Df	Ldf;
    //   228: ldc 112
    //   230: aload_2
    //   231: invokevirtual 124	df:a	(Ljava/lang/String;Ljava/lang/String;)V
    //   234: aload_0
    //   235: getfield 22	dq:jdField_a_of_type_ComArrownockPushIAnPushRegistrationCallback	Lcom/arrownock/push/IAnPushRegistrationCallback;
    //   238: ifnull +13 -> 251
    //   241: aload_0
    //   242: getfield 22	dq:jdField_a_of_type_ComArrownockPushIAnPushRegistrationCallback	Lcom/arrownock/push/IAnPushRegistrationCallback;
    //   245: aload_2
    //   246: invokeinterface 129 2 0
    //   251: return
    //   252: astore_3
    //   253: aload_0
    //   254: getfield 22	dq:jdField_a_of_type_ComArrownockPushIAnPushRegistrationCallback	Lcom/arrownock/push/IAnPushRegistrationCallback;
    //   257: ifnull -109 -> 148
    //   260: aload_0
    //   261: getfield 22	dq:jdField_a_of_type_ComArrownockPushIAnPushRegistrationCallback	Lcom/arrownock/push/IAnPushRegistrationCallback;
    //   264: astore_2
    //   265: new 37	com/arrownock/exception/ArrownockException
    //   268: astore 4
    //   270: aload 4
    //   272: aload_3
    //   273: invokevirtual 132	java/io/IOException:getMessage	()Ljava/lang/String;
    //   276: sipush 2003
    //   279: invokespecial 135	com/arrownock/exception/ArrownockException:<init>	(Ljava/lang/String;I)V
    //   282: aload_2
    //   283: aload 4
    //   285: invokeinterface 139 2 0
    //   290: goto -39 -> 251
    //   293: astore_2
    //   294: aload_0
    //   295: getfield 22	dq:jdField_a_of_type_ComArrownockPushIAnPushRegistrationCallback	Lcom/arrownock/push/IAnPushRegistrationCallback;
    //   298: ifnull -47 -> 251
    //   301: aload_0
    //   302: getfield 22	dq:jdField_a_of_type_ComArrownockPushIAnPushRegistrationCallback	Lcom/arrownock/push/IAnPushRegistrationCallback;
    //   305: aload_2
    //   306: invokeinterface 139 2 0
    //   311: goto -60 -> 251
    //   314: aload_0
    //   315: getfield 18	dq:jdField_a_of_type_Df	Ldf;
    //   318: ldc -115
    //   320: invokevirtual 144	df:a	(Ljava/lang/String;)Ljava/lang/String;
    //   323: aload_0
    //   324: getfield 18	dq:jdField_a_of_type_Df	Ldf;
    //   327: invokestatic 57	df:a	(Ldf;)Landroid/content/Context;
    //   330: invokestatic 78	com/arrownock/push/AnPush:getInstance	(Landroid/content/Context;)Lcom/arrownock/push/AnPush;
    //   333: invokevirtual 82	com/arrownock/push/AnPush:getSenderId	()Ljava/lang/String;
    //   336: invokevirtual 49	java/lang/String:equals	(Ljava/lang/Object;)Z
    //   339: istore_1
    //   340: aload_3
    //   341: astore_2
    //   342: iload_1
    //   343: ifne -195 -> 148
    //   346: aload_3
    //   347: astore_2
    //   348: aload_0
    //   349: getfield 18	dq:jdField_a_of_type_Df	Ldf;
    //   352: invokestatic 57	df:a	(Ldf;)Landroid/content/Context;
    //   355: invokestatic 70	com/google/android/gms/gcm/GoogleCloudMessaging:getInstance	(Landroid/content/Context;)Lcom/google/android/gms/gcm/GoogleCloudMessaging;
    //   358: astore 4
    //   360: aload_3
    //   361: astore_2
    //   362: aload 4
    //   364: invokevirtual 73	com/google/android/gms/gcm/GoogleCloudMessaging:unregister	()V
    //   367: aload_3
    //   368: astore_2
    //   369: aload 4
    //   371: iconst_1
    //   372: anewarray 45	java/lang/String
    //   375: dup
    //   376: iconst_0
    //   377: aload_0
    //   378: getfield 18	dq:jdField_a_of_type_Df	Ldf;
    //   381: invokestatic 57	df:a	(Ldf;)Landroid/content/Context;
    //   384: invokestatic 78	com/arrownock/push/AnPush:getInstance	(Landroid/content/Context;)Lcom/arrownock/push/AnPush;
    //   387: invokevirtual 82	com/arrownock/push/AnPush:getSenderId	()Ljava/lang/String;
    //   390: aastore
    //   391: invokevirtual 86	com/google/android/gms/gcm/GoogleCloudMessaging:register	([Ljava/lang/String;)Ljava/lang/String;
    //   394: astore_3
    //   395: aload_3
    //   396: astore_2
    //   397: new 88	java/lang/StringBuilder
    //   400: astore 4
    //   402: aload_3
    //   403: astore_2
    //   404: aload 4
    //   406: ldc -110
    //   408: invokespecial 93	java/lang/StringBuilder:<init>	(Ljava/lang/String;)V
    //   411: aload_3
    //   412: astore_2
    //   413: ldc 95
    //   415: aload 4
    //   417: aload_3
    //   418: invokevirtual 99	java/lang/StringBuilder:append	(Ljava/lang/String;)Ljava/lang/StringBuilder;
    //   421: invokevirtual 102	java/lang/StringBuilder:toString	()Ljava/lang/String;
    //   424: invokestatic 107	android/util/Log:d	(Ljava/lang/String;Ljava/lang/String;)I
    //   427: pop
    //   428: aload_3
    //   429: astore_2
    //   430: aload_0
    //   431: getfield 18	dq:jdField_a_of_type_Df	Ldf;
    //   434: aload_0
    //   435: getfield 18	dq:jdField_a_of_type_Df	Ldf;
    //   438: invokestatic 57	df:a	(Ldf;)Landroid/content/Context;
    //   441: aload_3
    //   442: invokestatic 110	df:a	(Ldf;Landroid/content/Context;Ljava/lang/String;)V
    //   445: aload_3
    //   446: astore_2
    //   447: goto -299 -> 148
    //   450: astore_3
    //   451: aload_0
    //   452: getfield 22	dq:jdField_a_of_type_ComArrownockPushIAnPushRegistrationCallback	Lcom/arrownock/push/IAnPushRegistrationCallback;
    //   455: ifnull -307 -> 148
    //   458: aload_0
    //   459: getfield 22	dq:jdField_a_of_type_ComArrownockPushIAnPushRegistrationCallback	Lcom/arrownock/push/IAnPushRegistrationCallback;
    //   462: astore_2
    //   463: new 37	com/arrownock/exception/ArrownockException
    //   466: astore 4
    //   468: aload 4
    //   470: aload_3
    //   471: invokevirtual 132	java/io/IOException:getMessage	()Ljava/lang/String;
    //   474: sipush 2003
    //   477: invokespecial 135	com/arrownock/exception/ArrownockException:<init>	(Ljava/lang/String;I)V
    //   480: aload_2
    //   481: aload 4
    //   483: invokeinterface 139 2 0
    //   488: goto -237 -> 251
    //   491: aload_0
    //   492: getfield 24	dq:b	Ljava/lang/String;
    //   495: astore_3
    //   496: goto -298 -> 198
    //   499: aload_0
    //   500: getfield 22	dq:jdField_a_of_type_ComArrownockPushIAnPushRegistrationCallback	Lcom/arrownock/push/IAnPushRegistrationCallback;
    //   503: ifnull -252 -> 251
    //   506: aload_0
    //   507: getfield 22	dq:jdField_a_of_type_ComArrownockPushIAnPushRegistrationCallback	Lcom/arrownock/push/IAnPushRegistrationCallback;
    //   510: astore_2
    //   511: new 37	com/arrownock/exception/ArrownockException
    //   514: astore_3
    //   515: aload_3
    //   516: ldc -108
    //   518: sipush 2003
    //   521: invokespecial 135	com/arrownock/exception/ArrownockException:<init>	(Ljava/lang/String;I)V
    //   524: aload_2
    //   525: aload_3
    //   526: invokeinterface 139 2 0
    //   531: goto -280 -> 251
    //   534: aload_0
    //   535: getfield 20	dq:jdField_a_of_type_JavaLangString	Ljava/lang/String;
    //   538: ldc -106
    //   540: invokevirtual 49	java/lang/String:equals	(Ljava/lang/Object;)Z
    //   543: ifeq +234 -> 777
    //   546: aload_0
    //   547: getfield 18	dq:jdField_a_of_type_Df	Ldf;
    //   550: aload_0
    //   551: getfield 26	dq:c	Ljava/lang/String;
    //   554: aload_0
    //   555: getfield 24	dq:b	Ljava/lang/String;
    //   558: invokestatic 153	df:a	(Ldf;Ljava/lang/String;Ljava/lang/String;)Ljava/lang/String;
    //   561: astore 5
    //   563: aload 5
    //   565: ifnull +198 -> 763
    //   568: ldc -101
    //   570: aload 5
    //   572: invokevirtual 158	java/lang/String:trim	()Ljava/lang/String;
    //   575: invokevirtual 49	java/lang/String:equals	(Ljava/lang/Object;)Z
    //   578: ifne +185 -> 763
    //   581: aload_0
    //   582: getfield 18	dq:jdField_a_of_type_Df	Ldf;
    //   585: ldc 112
    //   587: aconst_null
    //   588: invokevirtual 115	df:a	(Ljava/lang/String;Ljava/lang/String;)Ljava/lang/String;
    //   591: astore 4
    //   593: aload_0
    //   594: getfield 24	dq:b	Ljava/lang/String;
    //   597: ifnonnull +128 -> 725
    //   600: aload 4
    //   602: astore_2
    //   603: aload 4
    //   605: ifnonnull +33 -> 638
    //   608: aload_0
    //   609: getfield 18	dq:jdField_a_of_type_Df	Ldf;
    //   612: aload_0
    //   613: getfield 18	dq:jdField_a_of_type_Df	Ldf;
    //   616: invokestatic 57	df:a	(Ldf;)Landroid/content/Context;
    //   619: aload_0
    //   620: getfield 26	dq:c	Ljava/lang/String;
    //   623: invokevirtual 118	df:a	(Landroid/content/Context;Ljava/lang/String;)Ljava/lang/String;
    //   626: astore 4
    //   628: aload_3
    //   629: astore_2
    //   630: aload 4
    //   632: ifnull +6 -> 638
    //   635: aload 4
    //   637: astore_2
    //   638: aload_0
    //   639: getfield 18	dq:jdField_a_of_type_Df	Ldf;
    //   642: aload_0
    //   643: getfield 26	dq:c	Ljava/lang/String;
    //   646: aload 5
    //   648: aload_0
    //   649: getfield 28	dq:d	Ljava/lang/String;
    //   652: aload_0
    //   653: getfield 30	dq:jdField_a_of_type_Boolean	Z
    //   656: aload_0
    //   657: getfield 20	dq:jdField_a_of_type_JavaLangString	Ljava/lang/String;
    //   660: aload_2
    //   661: invokevirtual 121	df:a	(Ljava/lang/String;Ljava/lang/String;Ljava/lang/String;ZLjava/lang/String;Ljava/lang/String;)Ljava/lang/String;
    //   664: astore_3
    //   665: ldc -96
    //   667: aload_3
    //   668: invokevirtual 49	java/lang/String:equals	(Ljava/lang/Object;)Z
    //   671: ifeq +62 -> 733
    //   674: invokestatic 165	bk:a	()Lbk;
    //   677: invokestatic 167	df:b	()Ljava/lang/String;
    //   680: ldc -87
    //   682: invokevirtual 170	bk:a	(Ljava/lang/String;Ljava/lang/String;)V
    //   685: aload_0
    //   686: getfield 18	dq:jdField_a_of_type_Df	Ldf;
    //   689: ldc -84
    //   691: invokevirtual 174	df:a	(Ljava/lang/String;)V
    //   694: aload_0
    //   695: getfield 18	dq:jdField_a_of_type_Df	Ldf;
    //   698: aload_0
    //   699: getfield 26	dq:c	Ljava/lang/String;
    //   702: aload_0
    //   703: getfield 28	dq:d	Ljava/lang/String;
    //   706: aload_0
    //   707: getfield 22	dq:jdField_a_of_type_ComArrownockPushIAnPushRegistrationCallback	Lcom/arrownock/push/IAnPushRegistrationCallback;
    //   710: aload_0
    //   711: getfield 30	dq:jdField_a_of_type_Boolean	Z
    //   714: aload_0
    //   715: getfield 20	dq:jdField_a_of_type_JavaLangString	Ljava/lang/String;
    //   718: aload_2
    //   719: invokevirtual 177	df:a	(Ljava/lang/String;Ljava/lang/String;Lcom/arrownock/push/IAnPushRegistrationCallback;ZLjava/lang/String;Ljava/lang/String;)V
    //   722: goto -471 -> 251
    //   725: aload_0
    //   726: getfield 24	dq:b	Ljava/lang/String;
    //   729: astore_2
    //   730: goto -92 -> 638
    //   733: aload_0
    //   734: getfield 18	dq:jdField_a_of_type_Df	Ldf;
    //   737: ldc 112
    //   739: aload_3
    //   740: invokevirtual 124	df:a	(Ljava/lang/String;Ljava/lang/String;)V
    //   743: aload_0
    //   744: getfield 22	dq:jdField_a_of_type_ComArrownockPushIAnPushRegistrationCallback	Lcom/arrownock/push/IAnPushRegistrationCallback;
    //   747: ifnull -496 -> 251
    //   750: aload_0
    //   751: getfield 22	dq:jdField_a_of_type_ComArrownockPushIAnPushRegistrationCallback	Lcom/arrownock/push/IAnPushRegistrationCallback;
    //   754: aload_3
    //   755: invokeinterface 129 2 0
    //   760: goto -509 -> 251
    //   763: invokestatic 165	bk:a	()Lbk;
    //   766: invokestatic 167	df:b	()Ljava/lang/String;
    //   769: ldc -77
    //   771: invokevirtual 181	bk:c	(Ljava/lang/String;Ljava/lang/String;)V
    //   774: goto -523 -> 251
    //   777: aload_0
    //   778: getfield 20	dq:jdField_a_of_type_JavaLangString	Ljava/lang/String;
    //   781: ldc -73
    //   783: invokevirtual 49	java/lang/String:equals	(Ljava/lang/Object;)Z
    //   786: ifeq -535 -> 251
    //   789: aload_0
    //   790: getfield 18	dq:jdField_a_of_type_Df	Ldf;
    //   793: astore_2
    //   794: aload_0
    //   795: getfield 18	dq:jdField_a_of_type_Df	Ldf;
    //   798: invokestatic 57	df:a	(Ldf;)Landroid/content/Context;
    //   801: pop
    //   802: aload_2
    //   803: invokevirtual 185	df:a	()Ljava/lang/String;
    //   806: astore_2
    //   807: aload_0
    //   808: getfield 18	dq:jdField_a_of_type_Df	Ldf;
    //   811: invokestatic 57	df:a	(Ldf;)Landroid/content/Context;
    //   814: invokestatic 78	com/arrownock/push/AnPush:getInstance	(Landroid/content/Context;)Lcom/arrownock/push/AnPush;
    //   817: astore 6
    //   819: aload 6
    //   821: monitorenter
    //   822: aload_2
    //   823: astore_3
    //   824: ldc -101
    //   826: aload_2
    //   827: invokevirtual 49	java/lang/String:equals	(Ljava/lang/Object;)Z
    //   830: ifeq +78 -> 908
    //   833: aload_0
    //   834: getfield 18	dq:jdField_a_of_type_Df	Ldf;
    //   837: invokestatic 57	df:a	(Ldf;)Landroid/content/Context;
    //   840: aload_0
    //   841: getfield 18	dq:jdField_a_of_type_Df	Ldf;
    //   844: ldc -69
    //   846: invokevirtual 144	df:a	(Ljava/lang/String;)Ljava/lang/String;
    //   849: aload_0
    //   850: getfield 18	dq:jdField_a_of_type_Df	Ldf;
    //   853: ldc -67
    //   855: invokevirtual 144	df:a	(Ljava/lang/String;)Ljava/lang/String;
    //   858: invokestatic 195	com/xiaomi/mipush/sdk/MiPushClient:registerPush	(Landroid/content/Context;Ljava/lang/String;Ljava/lang/String;)V
    //   861: aload_2
    //   862: ldc -101
    //   864: invokevirtual 49	java/lang/String:equals	(Ljava/lang/Object;)Z
    //   867: istore_1
    //   868: aload_2
    //   869: astore_3
    //   870: iload_1
    //   871: ifeq +37 -> 908
    //   874: aload_0
    //   875: getfield 18	dq:jdField_a_of_type_Df	Ldf;
    //   878: invokestatic 57	df:a	(Ldf;)Landroid/content/Context;
    //   881: invokestatic 78	com/arrownock/push/AnPush:getInstance	(Landroid/content/Context;)Lcom/arrownock/push/AnPush;
    //   884: invokevirtual 198	java/lang/Object:wait	()V
    //   887: aload_0
    //   888: getfield 18	dq:jdField_a_of_type_Df	Ldf;
    //   891: astore_2
    //   892: aload_0
    //   893: getfield 18	dq:jdField_a_of_type_Df	Ldf;
    //   896: invokestatic 57	df:a	(Ldf;)Landroid/content/Context;
    //   899: pop
    //   900: aload_2
    //   901: invokevirtual 185	df:a	()Ljava/lang/String;
    //   904: astore_2
    //   905: goto -44 -> 861
    //   908: aload_0
    //   909: getfield 18	dq:jdField_a_of_type_Df	Ldf;
    //   912: ldc 112
    //   914: aconst_null
    //   915: invokevirtual 115	df:a	(Ljava/lang/String;Ljava/lang/String;)Ljava/lang/String;
    //   918: astore 5
    //   920: aload_0
    //   921: getfield 24	dq:b	Ljava/lang/String;
    //   924: ifnonnull +107 -> 1031
    //   927: aload 5
    //   929: astore_2
    //   930: aload 5
    //   932: ifnonnull +34 -> 966
    //   935: aload_0
    //   936: getfield 18	dq:jdField_a_of_type_Df	Ldf;
    //   939: aload_0
    //   940: getfield 18	dq:jdField_a_of_type_Df	Ldf;
    //   943: invokestatic 57	df:a	(Ldf;)Landroid/content/Context;
    //   946: aload_0
    //   947: getfield 26	dq:c	Ljava/lang/String;
    //   950: invokevirtual 118	df:a	(Landroid/content/Context;Ljava/lang/String;)Ljava/lang/String;
    //   953: astore 5
    //   955: aload 4
    //   957: astore_2
    //   958: aload 5
    //   960: ifnull +6 -> 966
    //   963: aload 5
    //   965: astore_2
    //   966: aload_0
    //   967: getfield 18	dq:jdField_a_of_type_Df	Ldf;
    //   970: aload_0
    //   971: getfield 26	dq:c	Ljava/lang/String;
    //   974: aload_3
    //   975: aload_0
    //   976: getfield 28	dq:d	Ljava/lang/String;
    //   979: aload_0
    //   980: getfield 30	dq:jdField_a_of_type_Boolean	Z
    //   983: aload_0
    //   984: getfield 20	dq:jdField_a_of_type_JavaLangString	Ljava/lang/String;
    //   987: aload_2
    //   988: invokevirtual 121	df:a	(Ljava/lang/String;Ljava/lang/String;Ljava/lang/String;ZLjava/lang/String;Ljava/lang/String;)Ljava/lang/String;
    //   991: astore_2
    //   992: aload_0
    //   993: getfield 18	dq:jdField_a_of_type_Df	Ldf;
    //   996: ldc 112
    //   998: aload_2
    //   999: invokevirtual 124	df:a	(Ljava/lang/String;Ljava/lang/String;)V
    //   1002: aload_0
    //   1003: getfield 22	dq:jdField_a_of_type_ComArrownockPushIAnPushRegistrationCallback	Lcom/arrownock/push/IAnPushRegistrationCallback;
    //   1006: ifnull +13 -> 1019
    //   1009: aload_0
    //   1010: getfield 22	dq:jdField_a_of_type_ComArrownockPushIAnPushRegistrationCallback	Lcom/arrownock/push/IAnPushRegistrationCallback;
    //   1013: aload_2
    //   1014: invokeinterface 129 2 0
    //   1019: aload 6
    //   1021: monitorexit
    //   1022: goto -771 -> 251
    //   1025: astore_2
    //   1026: aload 6
    //   1028: monitorexit
    //   1029: aload_2
    //   1030: athrow
    //   1031: aload_0
    //   1032: getfield 24	dq:b	Ljava/lang/String;
    //   1035: astore_2
    //   1036: goto -70 -> 966
    //   1039: astore_2
    //   1040: goto -153 -> 887
    //   1043: aconst_null
    //   1044: astore_3
    //   1045: goto -847 -> 198
    // Local variable table:
    //   start	length	slot	name	signature
    //   0	1048	0	this	dq
    //   339	532	1	bool	boolean
    //   62	221	2	localObject1	Object
    //   293	13	2	localArrownockException	com.arrownock.exception.ArrownockException
    //   341	673	2	localObject2	Object
    //   1025	5	2	localObject3	Object
    //   1035	1	2	str1	String
    //   1039	1	2	localInterruptedException	InterruptedException
    //   4	216	3	localObject4	Object
    //   252	116	3	localIOException1	java.io.IOException
    //   394	52	3	str2	String
    //   450	21	3	localIOException2	java.io.IOException
    //   495	550	3	localObject5	Object
    //   1	955	4	localObject6	Object
    //   561	403	5	str3	String
    //   817	210	6	localAnPush	com.arrownock.push.AnPush
    // Exception table:
    //   from	to	target	type
    //   63	68	252	java/io/IOException
    //   70	96	252	java/io/IOException
    //   98	103	252	java/io/IOException
    //   105	112	252	java/io/IOException
    //   114	129	252	java/io/IOException
    //   131	146	252	java/io/IOException
    //   5	61	293	com/arrownock/exception/ArrownockException
    //   63	68	293	com/arrownock/exception/ArrownockException
    //   70	96	293	com/arrownock/exception/ArrownockException
    //   98	103	293	com/arrownock/exception/ArrownockException
    //   105	112	293	com/arrownock/exception/ArrownockException
    //   114	129	293	com/arrownock/exception/ArrownockException
    //   131	146	293	com/arrownock/exception/ArrownockException
    //   148	167	293	com/arrownock/exception/ArrownockException
    //   175	194	293	com/arrownock/exception/ArrownockException
    //   198	251	293	com/arrownock/exception/ArrownockException
    //   253	290	293	com/arrownock/exception/ArrownockException
    //   314	340	293	com/arrownock/exception/ArrownockException
    //   348	360	293	com/arrownock/exception/ArrownockException
    //   362	367	293	com/arrownock/exception/ArrownockException
    //   369	395	293	com/arrownock/exception/ArrownockException
    //   397	402	293	com/arrownock/exception/ArrownockException
    //   404	411	293	com/arrownock/exception/ArrownockException
    //   413	428	293	com/arrownock/exception/ArrownockException
    //   430	445	293	com/arrownock/exception/ArrownockException
    //   451	488	293	com/arrownock/exception/ArrownockException
    //   491	496	293	com/arrownock/exception/ArrownockException
    //   499	531	293	com/arrownock/exception/ArrownockException
    //   534	563	293	com/arrownock/exception/ArrownockException
    //   568	600	293	com/arrownock/exception/ArrownockException
    //   608	628	293	com/arrownock/exception/ArrownockException
    //   638	722	293	com/arrownock/exception/ArrownockException
    //   725	730	293	com/arrownock/exception/ArrownockException
    //   733	760	293	com/arrownock/exception/ArrownockException
    //   763	774	293	com/arrownock/exception/ArrownockException
    //   777	822	293	com/arrownock/exception/ArrownockException
    //   1026	1031	293	com/arrownock/exception/ArrownockException
    //   348	360	450	java/io/IOException
    //   362	367	450	java/io/IOException
    //   369	395	450	java/io/IOException
    //   397	402	450	java/io/IOException
    //   404	411	450	java/io/IOException
    //   413	428	450	java/io/IOException
    //   430	445	450	java/io/IOException
    //   824	861	1025	finally
    //   861	868	1025	finally
    //   874	887	1025	finally
    //   887	905	1025	finally
    //   908	927	1025	finally
    //   935	955	1025	finally
    //   966	1019	1025	finally
    //   1019	1022	1025	finally
    //   1031	1036	1025	finally
    //   874	887	1039	java/lang/InterruptedException
  }
}


/* Location:              E:\soft\ApkIDE\Worksrc\com.MobileTicket\!\dq.class
 * Java compiler version: 6 (50.0)
 * JD-Core Version:       0.7.1
 */