import java.io.IOException;
import java.util.Hashtable;

public final class js
{
  public int a;
  private Thread jdField_a_of_type_JavaLangThread = null;
  private jj jdField_a_of_type_Jj;
  jt jdField_a_of_type_Jt;
  public ju a;
  private jv jdField_a_of_type_Jv;
  private jw jdField_a_of_type_Jw;
  private jx jdField_a_of_type_Jx;
  jy jdField_a_of_type_Jy;
  public kc a;
  private kk jdField_a_of_type_Kk;
  public boolean a;
  private boolean b;
  
  public js(jy paramjy, jj paramjj, kk paramkk)
    throws jm
  {
    this.jdField_b_of_type_Boolean = false;
    this.jdField_a_of_type_Kk = paramkk;
    this.jdField_a_of_type_Ju = new ju(paramkk, this);
    this.jdField_a_of_type_Boolean = false;
    this.jdField_a_of_type_Jx = new jx(this.jdField_a_of_type_Kk);
    this.jdField_a_of_type_Jy = paramjy;
    this.jdField_a_of_type_Jt = new jt(paramkk, paramjj, this.jdField_a_of_type_Jx, this.jdField_a_of_type_Ju);
    this.jdField_a_of_type_Jj = paramjj;
  }
  
  /* Error */
  public final jl a(li arg1)
    throws jm
  {
    // Byte code:
    //   0: aload_0
    //   1: getfield 31	js:jdField_a_of_type_Kk	Lkk;
    //   4: invokevirtual 66	kk:a	()Z
    //   7: ifeq +27 -> 34
    //   10: aload_0
    //   11: getfield 31	js:jdField_a_of_type_Kk	Lkk;
    //   14: sipush 200
    //   17: iconst_1
    //   18: anewarray 4	java/lang/Object
    //   21: dup
    //   22: iconst_0
    //   23: aload_1
    //   24: invokevirtual 70	java/lang/Object:getClass	()Ljava/lang/Class;
    //   27: invokevirtual 76	java/lang/Class:getName	()Ljava/lang/String;
    //   30: aastore
    //   31: invokevirtual 79	kk:a	(I[Ljava/lang/Object;)V
    //   34: aload_0
    //   35: getfield 27	js:jdField_b_of_type_Boolean	Z
    //   38: ifne +358 -> 396
    //   41: aload_0
    //   42: getfield 40	js:jdField_a_of_type_Boolean	Z
    //   45: ifeq +351 -> 396
    //   48: aload_0
    //   49: getfield 56	js:jdField_a_of_type_Jt	Ljt;
    //   52: aload_1
    //   53: invokevirtual 81	jt:a	(Lli;)Ljl;
    //   56: astore 5
    //   58: aload_1
    //   59: instanceof 83
    //   62: ifeq +90 -> 152
    //   65: aload_0
    //   66: getfield 56	js:jdField_a_of_type_Jt	Ljt;
    //   69: astore 4
    //   71: aload 4
    //   73: getfield 87	jt:jdField_c_of_type_JavaLangObject	Ljava/lang/Object;
    //   76: astore_2
    //   77: aload_2
    //   78: monitorenter
    //   79: aload 4
    //   81: aload 4
    //   83: getfield 89	jt:jdField_c_of_type_Int	I
    //   86: iconst_1
    //   87: iadd
    //   88: putfield 89	jt:jdField_c_of_type_Int	I
    //   91: aload 4
    //   93: getfield 90	jt:jdField_a_of_type_Kk	Lkk;
    //   96: invokevirtual 66	kk:a	()Z
    //   99: ifeq +39 -> 138
    //   102: aload 4
    //   104: getfield 90	jt:jdField_a_of_type_Kk	Lkk;
    //   107: astore 6
    //   109: new 92	java/lang/Integer
    //   112: astore_3
    //   113: aload_3
    //   114: aload 4
    //   116: getfield 89	jt:jdField_c_of_type_Int	I
    //   119: invokespecial 95	java/lang/Integer:<init>	(I)V
    //   122: aload 6
    //   124: sipush 642
    //   127: iconst_1
    //   128: anewarray 4	java/lang/Object
    //   131: dup
    //   132: iconst_0
    //   133: aload_3
    //   134: aastore
    //   135: invokevirtual 79	kk:a	(I[Ljava/lang/Object;)V
    //   138: aload_2
    //   139: monitorexit
    //   140: aload 5
    //   142: invokevirtual 99	jl:a	()V
    //   145: aload_0
    //   146: getfield 56	js:jdField_a_of_type_Jt	Ljt;
    //   149: invokevirtual 100	jt:a	()V
    //   152: aload 5
    //   154: areturn
    //   155: astore_3
    //   156: aload_2
    //   157: monitorexit
    //   158: aload_3
    //   159: athrow
    //   160: astore_2
    //   161: aload_0
    //   162: getfield 31	js:jdField_a_of_type_Kk	Lkk;
    //   165: invokevirtual 66	kk:a	()Z
    //   168: ifeq +15 -> 183
    //   171: aload_0
    //   172: getfield 31	js:jdField_a_of_type_Kk	Lkk;
    //   175: sipush 202
    //   178: aconst_null
    //   179: aload_2
    //   180: invokevirtual 103	kk:a	(I[Ljava/lang/Object;Ljava/lang/Throwable;)V
    //   183: aload_0
    //   184: getfield 56	js:jdField_a_of_type_Jt	Ljt;
    //   187: astore_3
    //   188: aload_1
    //   189: checkcast 83	lc
    //   192: astore 4
    //   194: aload_3
    //   195: getfield 105	jt:jdField_a_of_type_JavaLangObject	Ljava/lang/Object;
    //   198: astore_1
    //   199: aload_1
    //   200: monitorenter
    //   201: aload_3
    //   202: getfield 90	jt:jdField_a_of_type_Kk	Lkk;
    //   205: invokevirtual 66	kk:a	()Z
    //   208: ifeq +64 -> 272
    //   211: aload_3
    //   212: getfield 90	jt:jdField_a_of_type_Kk	Lkk;
    //   215: astore 5
    //   217: new 92	java/lang/Integer
    //   220: astore 6
    //   222: aload 6
    //   224: aload 4
    //   226: getfield 108	lc:a	Ljn;
    //   229: getfield 112	jn:jdField_a_of_type_Int	I
    //   232: invokespecial 95	java/lang/Integer:<init>	(I)V
    //   235: new 92	java/lang/Integer
    //   238: astore 7
    //   240: aload 7
    //   242: aload 4
    //   244: invokevirtual 115	lc:c	()I
    //   247: invokespecial 95	java/lang/Integer:<init>	(I)V
    //   250: aload 5
    //   252: sipush 618
    //   255: iconst_2
    //   256: anewarray 4	java/lang/Object
    //   259: dup
    //   260: iconst_0
    //   261: aload 6
    //   263: aastore
    //   264: dup
    //   265: iconst_1
    //   266: aload 7
    //   268: aastore
    //   269: invokevirtual 79	kk:a	(I[Ljava/lang/Object;)V
    //   272: aload 4
    //   274: getfield 108	lc:a	Ljn;
    //   277: getfield 112	jn:jdField_a_of_type_Int	I
    //   280: iconst_1
    //   281: if_icmpne +78 -> 359
    //   284: aload_3
    //   285: getfield 118	jt:jdField_b_of_type_JavaUtilHashtable	Ljava/util/Hashtable;
    //   288: astore 6
    //   290: new 92	java/lang/Integer
    //   293: astore 5
    //   295: aload 5
    //   297: aload 4
    //   299: invokevirtual 115	lc:c	()I
    //   302: invokespecial 95	java/lang/Integer:<init>	(I)V
    //   305: aload 6
    //   307: aload 5
    //   309: invokevirtual 124	java/util/Hashtable:remove	(Ljava/lang/Object;)Ljava/lang/Object;
    //   312: pop
    //   313: aload_3
    //   314: getfield 127	jt:jdField_a_of_type_JavaUtilVector	Ljava/util/Vector;
    //   317: aload 4
    //   319: invokevirtual 133	java/util/Vector:removeElement	(Ljava/lang/Object;)Z
    //   322: pop
    //   323: aload_3
    //   324: getfield 134	jt:jdField_a_of_type_Jj	Ljj;
    //   327: aload 4
    //   329: invokestatic 137	jt:a	(Lli;)Ljava/lang/String;
    //   332: invokevirtual 142	jj:a	(Ljava/lang/String;)V
    //   335: aload_3
    //   336: getfield 143	jt:jdField_a_of_type_Jx	Ljx;
    //   339: aload 4
    //   341: invokevirtual 145	jx:c	(Lli;)Ljl;
    //   344: pop
    //   345: aload_1
    //   346: monitorexit
    //   347: aload_2
    //   348: athrow
    //   349: astore_1
    //   350: aload_0
    //   351: getfield 56	js:jdField_a_of_type_Jt	Ljt;
    //   354: invokevirtual 100	jt:a	()V
    //   357: aload_1
    //   358: athrow
    //   359: aload_3
    //   360: getfield 147	jt:jdField_a_of_type_JavaUtilHashtable	Ljava/util/Hashtable;
    //   363: astore 5
    //   365: new 92	java/lang/Integer
    //   368: astore 6
    //   370: aload 6
    //   372: aload 4
    //   374: invokevirtual 115	lc:c	()I
    //   377: invokespecial 95	java/lang/Integer:<init>	(I)V
    //   380: aload 5
    //   382: aload 6
    //   384: invokevirtual 124	java/util/Hashtable:remove	(Ljava/lang/Object;)Ljava/lang/Object;
    //   387: pop
    //   388: goto -75 -> 313
    //   391: astore_2
    //   392: aload_1
    //   393: monitorexit
    //   394: aload_2
    //   395: athrow
    //   396: aload_0
    //   397: getfield 31	js:jdField_a_of_type_Kk	Lkk;
    //   400: sipush 208
    //   403: iconst_2
    //   404: anewarray 4	java/lang/Object
    //   407: dup
    //   408: iconst_0
    //   409: new 149	java/lang/Boolean
    //   412: dup
    //   413: aload_0
    //   414: getfield 27	js:jdField_b_of_type_Boolean	Z
    //   417: invokespecial 152	java/lang/Boolean:<init>	(Z)V
    //   420: aastore
    //   421: dup
    //   422: iconst_1
    //   423: new 149	java/lang/Boolean
    //   426: dup
    //   427: aload_0
    //   428: getfield 40	js:jdField_a_of_type_Boolean	Z
    //   431: invokespecial 152	java/lang/Boolean:<init>	(Z)V
    //   434: aastore
    //   435: invokevirtual 79	kk:a	(I[Ljava/lang/Object;)V
    //   438: sipush 32104
    //   441: invokestatic 157	at:a	(I)Ljm;
    //   444: athrow
    // Local variable table:
    //   start	length	slot	name	signature
    //   0	445	0	this	js
    //   160	188	2	localjm	jm
    //   391	4	2	localObject2	Object
    //   112	22	3	localInteger1	Integer
    //   155	4	3	localObject3	Object
    //   187	173	3	localjt	jt
    //   69	304	4	localObject4	Object
    //   56	325	5	localObject5	Object
    //   107	276	6	localObject6	Object
    //   238	29	7	localInteger2	Integer
    // Exception table:
    //   from	to	target	type
    //   79	138	155	finally
    //   138	140	155	finally
    //   65	79	160	jm
    //   140	145	160	jm
    //   156	160	160	jm
    //   65	79	349	finally
    //   140	145	349	finally
    //   156	160	349	finally
    //   161	183	349	finally
    //   183	201	349	finally
    //   347	349	349	finally
    //   392	396	349	finally
    //   201	272	391	finally
    //   272	313	391	finally
    //   313	347	391	finally
    //   359	388	391	finally
  }
  
  public final kq a(kr paramkr, int paramInt, long paramLong, boolean paramBoolean)
    throws jm
  {
    if (!this.jdField_a_of_type_Boolean)
    {
      this.jdField_b_of_type_Boolean = false;
      this.jdField_a_of_type_Int = paramInt;
      this.jdField_a_of_type_Jt.jdField_a_of_type_Long = (1000L * paramLong);
      this.jdField_a_of_type_Jt.jdField_a_of_type_Boolean = paramBoolean;
      Object localObject;
      try
      {
        this.jdField_a_of_type_Kc.a();
        localObject = new jv;
        ((jv)localObject).<init>(this.jdField_a_of_type_Kk, this, this.jdField_a_of_type_Jt, this.jdField_a_of_type_Jx, this.jdField_a_of_type_Kc.a());
        this.jdField_a_of_type_Jv = ((jv)localObject);
        this.jdField_a_of_type_Jv.a();
        localObject = new jw;
        ((jw)localObject).<init>(this.jdField_a_of_type_Kk, this, this.jdField_a_of_type_Jt, this.jdField_a_of_type_Jx, this.jdField_a_of_type_Kc.a());
        this.jdField_a_of_type_Jw = ((jw)localObject);
        this.jdField_a_of_type_Jw.a();
        this.jdField_a_of_type_Ju.a();
        try
        {
          localObject = this.jdField_a_of_type_Jt.a(paramkr).a(paramInt * 1000);
          if (localObject == null)
          {
            this.jdField_a_of_type_Kk.a(203);
            this.jdField_a_of_type_Jj.jdField_a_of_type_JavaUtilHashtable.clear();
            throw at.a(32000);
          }
        }
        catch (jm paramkr)
        {
          this.jdField_a_of_type_Kk.a(206, null, paramkr);
          a(null);
          throw paramkr;
        }
        if (!(localObject instanceof kq)) {
          break label367;
        }
      }
      catch (IOException paramkr)
      {
        this.jdField_a_of_type_Kk.a(209, null, paramkr);
        this.jdField_a_of_type_Jj.jdField_a_of_type_JavaUtilHashtable.clear();
        throw at.a(paramkr);
      }
      catch (jm paramkr)
      {
        this.jdField_a_of_type_Kk.a(212, null, paramkr);
        this.jdField_a_of_type_Jj.jdField_a_of_type_JavaUtilHashtable.clear();
        throw paramkr;
      }
      paramkr = (kq)localObject;
      if (paramkr.jdField_a_of_type_Int != 0)
      {
        kk localkk = this.jdField_a_of_type_Kk;
        localObject = new java/lang/Integer;
        ((Integer)localObject).<init>(paramkr.jdField_a_of_type_Int);
        localkk.a(204, new Object[] { localObject });
        this.jdField_a_of_type_Jj.jdField_a_of_type_JavaUtilHashtable.clear();
        this.jdField_a_of_type_JavaLangThread = Thread.currentThread();
        a(null);
        throw at.a(paramkr.jdField_a_of_type_Int);
      }
      this.jdField_a_of_type_Boolean = true;
      return (kq)localObject;
      label367:
      this.jdField_a_of_type_Kk.a(205, new Object[] { localObject });
      this.jdField_a_of_type_Jj.jdField_a_of_type_JavaUtilHashtable.clear();
      throw at.a(6);
    }
    this.jdField_a_of_type_Kk.a(207);
    throw at.a(32100);
  }
  
  public final void a(jm paramjm)
  {
    if ((this.jdField_a_of_type_JavaLangThread != null) && (!this.jdField_a_of_type_JavaLangThread.equals(Thread.currentThread()))) {}
    for (;;)
    {
      return;
      if (this.jdField_a_of_type_Kk.a()) {
        this.jdField_a_of_type_Kk.a(201, new Object[] { new Boolean(this.jdField_b_of_type_Boolean) }, paramjm);
      }
      boolean bool;
      if (!this.jdField_b_of_type_Boolean)
      {
        bool = this.jdField_a_of_type_Boolean;
        this.jdField_b_of_type_Boolean = true;
        this.jdField_a_of_type_Jt.a(paramjm);
      }
      try
      {
        this.jdField_a_of_type_Ju.b();
        try
        {
          this.jdField_a_of_type_Kc.b();
          try
          {
            this.jdField_a_of_type_Jv.b();
            this.jdField_a_of_type_Jt.b(paramjm);
            try
            {
              this.jdField_a_of_type_Jw.b();
              this.jdField_a_of_type_Boolean = false;
              if ((!bool) || (paramjm == null)) {
                continue;
              }
              this.jdField_a_of_type_Ju.a(paramjm);
              continue;
              this.jdField_a_of_type_Boolean = false;
            }
            catch (IOException localIOException1)
            {
              for (;;) {}
            }
          }
          catch (IOException localIOException2)
          {
            for (;;) {}
          }
        }
        catch (IOException localIOException3)
        {
          for (;;) {}
        }
      }
      catch (IOException localIOException4)
      {
        for (;;) {}
      }
    }
  }
  
  /* Error */
  public final void a(ks paramks)
    throws jm
  {
    // Byte code:
    //   0: aload_0
    //   1: getfield 40	js:jdField_a_of_type_Boolean	Z
    //   4: ifeq +365 -> 369
    //   7: invokestatic 219	java/lang/Thread:currentThread	()Ljava/lang/Thread;
    //   10: aload_0
    //   11: getfield 38	js:jdField_a_of_type_Ju	Lju;
    //   14: invokevirtual 238	ju:a	()Ljava/lang/Thread;
    //   17: if_acmpne +20 -> 37
    //   20: aload_0
    //   21: getfield 31	js:jdField_a_of_type_Kk	Lkk;
    //   24: sipush 210
    //   27: invokevirtual 200	kk:a	(I)V
    //   30: sipush 32107
    //   33: invokestatic 157	at:a	(I)Ljm;
    //   36: athrow
    //   37: aload_0
    //   38: getfield 56	js:jdField_a_of_type_Jt	Ljt;
    //   41: astore_2
    //   42: aload_2
    //   43: getfield 90	jt:jdField_a_of_type_Kk	Lkk;
    //   46: sipush 637
    //   49: iconst_1
    //   50: anewarray 4	java/lang/Object
    //   53: dup
    //   54: iconst_0
    //   55: new 240	java/lang/Long
    //   58: dup
    //   59: ldc2_w 241
    //   62: invokespecial 245	java/lang/Long:<init>	(J)V
    //   65: aastore
    //   66: invokevirtual 79	kk:a	(I[Ljava/lang/Object;)V
    //   69: ldc2_w 241
    //   72: lconst_0
    //   73: lcmp
    //   74: ifle +226 -> 300
    //   77: aload_2
    //   78: getfield 105	jt:jdField_a_of_type_JavaLangObject	Ljava/lang/Object;
    //   81: astore_3
    //   82: aload_3
    //   83: monitorenter
    //   84: aload_2
    //   85: iconst_1
    //   86: putfield 246	jt:jdField_b_of_type_Boolean	Z
    //   89: aload_3
    //   90: monitorexit
    //   91: aload_2
    //   92: getfield 247	jt:jdField_a_of_type_Ju	Lju;
    //   95: invokevirtual 249	ju:c	()V
    //   98: aload_2
    //   99: getfield 105	jt:jdField_a_of_type_JavaLangObject	Ljava/lang/Object;
    //   102: astore_3
    //   103: aload_3
    //   104: monitorenter
    //   105: aload_2
    //   106: getfield 90	jt:jdField_a_of_type_Kk	Lkk;
    //   109: sipush 638
    //   112: invokevirtual 200	kk:a	(I)V
    //   115: aload_2
    //   116: getfield 105	jt:jdField_a_of_type_JavaLangObject	Ljava/lang/Object;
    //   119: invokevirtual 252	java/lang/Object:notifyAll	()V
    //   122: aload_3
    //   123: monitorexit
    //   124: aload_2
    //   125: getfield 254	jt:jdField_b_of_type_JavaLangObject	Ljava/lang/Object;
    //   128: astore_3
    //   129: aload_3
    //   130: monitorenter
    //   131: aload_2
    //   132: getfield 255	jt:jdField_a_of_type_Int	I
    //   135: ifgt +20 -> 155
    //   138: aload_2
    //   139: getfield 257	jt:jdField_b_of_type_JavaUtilVector	Ljava/util/Vector;
    //   142: invokevirtual 260	java/util/Vector:size	()I
    //   145: ifgt +10 -> 155
    //   148: aload_2
    //   149: getfield 262	jt:jdField_b_of_type_Int	I
    //   152: ifle +111 -> 263
    //   155: aload_2
    //   156: getfield 90	jt:jdField_a_of_type_Kk	Lkk;
    //   159: invokevirtual 66	kk:a	()Z
    //   162: ifeq +81 -> 243
    //   165: aload_2
    //   166: getfield 90	jt:jdField_a_of_type_Kk	Lkk;
    //   169: astore 6
    //   171: new 92	java/lang/Integer
    //   174: astore 5
    //   176: aload 5
    //   178: aload_2
    //   179: getfield 255	jt:jdField_a_of_type_Int	I
    //   182: invokespecial 95	java/lang/Integer:<init>	(I)V
    //   185: new 92	java/lang/Integer
    //   188: astore 4
    //   190: aload 4
    //   192: aload_2
    //   193: getfield 257	jt:jdField_b_of_type_JavaUtilVector	Ljava/util/Vector;
    //   196: invokevirtual 260	java/util/Vector:size	()I
    //   199: invokespecial 95	java/lang/Integer:<init>	(I)V
    //   202: new 92	java/lang/Integer
    //   205: astore 7
    //   207: aload 7
    //   209: aload_2
    //   210: getfield 262	jt:jdField_b_of_type_Int	I
    //   213: invokespecial 95	java/lang/Integer:<init>	(I)V
    //   216: aload 6
    //   218: sipush 639
    //   221: iconst_3
    //   222: anewarray 4	java/lang/Object
    //   225: dup
    //   226: iconst_0
    //   227: aload 5
    //   229: aastore
    //   230: dup
    //   231: iconst_1
    //   232: aload 4
    //   234: aastore
    //   235: dup
    //   236: iconst_2
    //   237: aload 7
    //   239: aastore
    //   240: invokevirtual 79	kk:a	(I[Ljava/lang/Object;)V
    //   243: aload_2
    //   244: getfield 254	jt:jdField_b_of_type_JavaLangObject	Ljava/lang/Object;
    //   247: ldc2_w 241
    //   250: invokevirtual 265	java/lang/Object:wait	(J)V
    //   253: aload_2
    //   254: getfield 90	jt:jdField_a_of_type_Kk	Lkk;
    //   257: sipush 640
    //   260: invokevirtual 200	kk:a	(I)V
    //   263: aload_3
    //   264: monitorexit
    //   265: aload_2
    //   266: getfield 105	jt:jdField_a_of_type_JavaLangObject	Ljava/lang/Object;
    //   269: astore_3
    //   270: aload_3
    //   271: monitorenter
    //   272: aload_2
    //   273: aload_2
    //   274: getfield 127	jt:jdField_a_of_type_JavaUtilVector	Ljava/util/Vector;
    //   277: invokevirtual 268	jt:a	(Ljava/util/Vector;)V
    //   280: aload_2
    //   281: aload_2
    //   282: getfield 257	jt:jdField_b_of_type_JavaUtilVector	Ljava/util/Vector;
    //   285: invokevirtual 268	jt:a	(Ljava/util/Vector;)V
    //   288: aload_2
    //   289: iconst_0
    //   290: putfield 246	jt:jdField_b_of_type_Boolean	Z
    //   293: aload_2
    //   294: iconst_0
    //   295: putfield 255	jt:jdField_a_of_type_Int	I
    //   298: aload_3
    //   299: monitorexit
    //   300: aload_0
    //   301: getfield 182	js:jdField_a_of_type_Jv	Ljv;
    //   304: invokevirtual 269	jv:c	()V
    //   307: aload_0
    //   308: invokestatic 219	java/lang/Thread:currentThread	()Ljava/lang/Thread;
    //   311: putfield 29	js:jdField_a_of_type_JavaLangThread	Ljava/lang/Thread;
    //   314: aload_0
    //   315: aload_1
    //   316: invokevirtual 270	js:a	(Lli;)Ljl;
    //   319: invokevirtual 99	jl:a	()V
    //   322: aload_0
    //   323: aconst_null
    //   324: invokevirtual 207	js:a	(Ljm;)V
    //   327: aload_0
    //   328: aconst_null
    //   329: putfield 29	js:jdField_a_of_type_JavaLangThread	Ljava/lang/Thread;
    //   332: return
    //   333: astore_1
    //   334: aload_3
    //   335: monitorexit
    //   336: aload_1
    //   337: athrow
    //   338: astore_1
    //   339: aload_3
    //   340: monitorexit
    //   341: aload_1
    //   342: athrow
    //   343: astore_1
    //   344: aload_3
    //   345: monitorexit
    //   346: aload_1
    //   347: athrow
    //   348: astore_1
    //   349: aload_3
    //   350: monitorexit
    //   351: aload_1
    //   352: athrow
    //   353: astore_1
    //   354: aload_1
    //   355: athrow
    //   356: astore_1
    //   357: aload_0
    //   358: aconst_null
    //   359: invokevirtual 207	js:a	(Ljm;)V
    //   362: aload_0
    //   363: aconst_null
    //   364: putfield 29	js:jdField_a_of_type_JavaLangThread	Ljava/lang/Thread;
    //   367: aload_1
    //   368: athrow
    //   369: aload_0
    //   370: getfield 31	js:jdField_a_of_type_Kk	Lkk;
    //   373: sipush 211
    //   376: invokevirtual 200	kk:a	(I)V
    //   379: sipush 32101
    //   382: invokestatic 157	at:a	(I)Ljm;
    //   385: athrow
    //   386: astore 4
    //   388: goto -125 -> 263
    // Local variable table:
    //   start	length	slot	name	signature
    //   0	391	0	this	js
    //   0	391	1	paramks	ks
    //   41	253	2	localjt	jt
    //   188	45	4	localInteger1	Integer
    //   386	1	4	localInterruptedException	InterruptedException
    //   174	54	5	localInteger2	Integer
    //   169	48	6	localkk	kk
    //   205	33	7	localInteger3	Integer
    // Exception table:
    //   from	to	target	type
    //   84	91	333	finally
    //   105	124	338	finally
    //   131	155	343	finally
    //   155	243	343	finally
    //   243	263	343	finally
    //   263	265	343	finally
    //   272	300	348	finally
    //   307	322	353	jm
    //   307	322	356	finally
    //   354	356	356	finally
    //   131	155	386	java/lang/InterruptedException
    //   155	243	386	java/lang/InterruptedException
    //   243	263	386	java/lang/InterruptedException
  }
}


/* Location:              E:\soft\ApkIDE\Worksrc\com.MobileTicket\!\js.class
 * Java compiler version: 6 (50.0)
 * JD-Core Version:       0.7.1
 */