import java.io.IOException;
import java.io.OutputStream;

public final class jw
  implements Runnable
{
  private Object jdField_a_of_type_JavaLangObject = new Object();
  private js jdField_a_of_type_Js = null;
  private jt jdField_a_of_type_Jt = null;
  private jx jdField_a_of_type_Jx = null;
  private kk jdField_a_of_type_Kk;
  private ku jdField_a_of_type_Ku;
  private boolean jdField_a_of_type_Boolean = false;
  
  public jw(kk paramkk, js paramjs, jt paramjt, jx paramjx, OutputStream paramOutputStream)
  {
    this.jdField_a_of_type_Kk = paramkk;
    this.jdField_a_of_type_Ku = new ku(paramOutputStream);
    this.jdField_a_of_type_Js = paramjs;
    this.jdField_a_of_type_Jt = paramjt;
    this.jdField_a_of_type_Jx = paramjx;
  }
  
  public final void a()
  {
    if (!this.jdField_a_of_type_Boolean)
    {
      this.jdField_a_of_type_Boolean = true;
      new Thread(this, "MQTT Client Comms Sender").start();
    }
  }
  
  public final void b()
    throws IOException
  {
    synchronized (this.jdField_a_of_type_JavaLangObject)
    {
      this.jdField_a_of_type_Kk.a(800);
      if (this.jdField_a_of_type_Boolean) {
        this.jdField_a_of_type_Boolean = false;
      }
    }
    try
    {
      this.jdField_a_of_type_Kk.a(801);
      this.jdField_a_of_type_JavaLangObject.wait();
      return;
      localObject2 = finally;
      throw ((Throwable)localObject2);
    }
    catch (InterruptedException localInterruptedException)
    {
      for (;;) {}
    }
  }
  
  /* Error */
  public final void run()
  {
    // Byte code:
    //   0: aconst_null
    //   1: astore_1
    //   2: aload_0
    //   3: getfield 21	jw:jdField_a_of_type_Boolean	Z
    //   6: ifeq +362 -> 368
    //   9: aload_0
    //   10: getfield 38	jw:jdField_a_of_type_Ku	Lku;
    //   13: ifnull +355 -> 368
    //   16: aload_1
    //   17: astore_3
    //   18: aload_1
    //   19: astore 4
    //   21: aload_0
    //   22: getfield 31	jw:jdField_a_of_type_Kk	Lkk;
    //   25: sipush 802
    //   28: invokevirtual 59	kk:a	(I)V
    //   31: aload_1
    //   32: astore_3
    //   33: aload_1
    //   34: astore 4
    //   36: aload_0
    //   37: getfield 25	jw:jdField_a_of_type_Jt	Ljt;
    //   40: invokevirtual 73	jt:a	()Lli;
    //   43: astore_2
    //   44: aload_2
    //   45: ifnull +270 -> 315
    //   48: aload_2
    //   49: astore_3
    //   50: aload_2
    //   51: astore 4
    //   53: aload_2
    //   54: instanceof 75
    //   57: ifeq +128 -> 185
    //   60: aload_2
    //   61: astore_3
    //   62: aload_2
    //   63: astore 4
    //   65: aload_0
    //   66: getfield 38	jw:jdField_a_of_type_Ku	Lku;
    //   69: aload_2
    //   70: invokevirtual 78	ku:a	(Lli;)V
    //   73: aload_2
    //   74: astore_3
    //   75: aload_2
    //   76: astore 4
    //   78: aload_0
    //   79: getfield 38	jw:jdField_a_of_type_Ku	Lku;
    //   82: invokevirtual 81	ku:flush	()V
    //   85: aload_2
    //   86: astore_1
    //   87: aload_2
    //   88: astore_3
    //   89: aload_2
    //   90: astore 4
    //   92: aload_2
    //   93: instanceof 83
    //   96: ifeq -94 -> 2
    //   99: aload_2
    //   100: astore_3
    //   101: aload_2
    //   102: astore 4
    //   104: aload_0
    //   105: getfield 23	jw:jdField_a_of_type_JavaLangObject	Ljava/lang/Object;
    //   108: astore 5
    //   110: aload_2
    //   111: astore_3
    //   112: aload_2
    //   113: astore 4
    //   115: aload 5
    //   117: monitorenter
    //   118: aload_0
    //   119: getfield 31	jw:jdField_a_of_type_Kk	Lkk;
    //   122: sipush 803
    //   125: invokevirtual 59	kk:a	(I)V
    //   128: aload_0
    //   129: iconst_0
    //   130: putfield 21	jw:jdField_a_of_type_Boolean	Z
    //   133: aload 5
    //   135: monitorexit
    //   136: aload_2
    //   137: astore_1
    //   138: goto -136 -> 2
    //   141: astore_1
    //   142: aload_2
    //   143: astore_3
    //   144: aload_2
    //   145: astore 4
    //   147: aload 5
    //   149: monitorexit
    //   150: aload_2
    //   151: astore_3
    //   152: aload_2
    //   153: astore 4
    //   155: aload_1
    //   156: athrow
    //   157: astore_2
    //   158: aload_0
    //   159: getfield 23	jw:jdField_a_of_type_JavaLangObject	Ljava/lang/Object;
    //   162: astore_1
    //   163: aload_1
    //   164: monitorenter
    //   165: aload_0
    //   166: iconst_0
    //   167: putfield 21	jw:jdField_a_of_type_Boolean	Z
    //   170: aload_1
    //   171: monitorexit
    //   172: aload_0
    //   173: getfield 27	jw:jdField_a_of_type_Js	Ljs;
    //   176: aload_2
    //   177: invokevirtual 88	js:a	(Ljm;)V
    //   180: aload_3
    //   181: astore_1
    //   182: goto -180 -> 2
    //   185: aload_2
    //   186: astore_3
    //   187: aload_2
    //   188: astore 4
    //   190: aload_0
    //   191: getfield 29	jw:jdField_a_of_type_Jx	Ljx;
    //   194: aload_2
    //   195: invokevirtual 93	jx:a	(Lli;)Ljl;
    //   198: astore 5
    //   200: aload_2
    //   201: astore_3
    //   202: aload_2
    //   203: astore 4
    //   205: aload 5
    //   207: monitorenter
    //   208: aload_0
    //   209: getfield 38	jw:jdField_a_of_type_Ku	Lku;
    //   212: aload_2
    //   213: invokevirtual 78	ku:a	(Lli;)V
    //   216: aload_0
    //   217: getfield 38	jw:jdField_a_of_type_Ku	Lku;
    //   220: invokevirtual 81	ku:flush	()V
    //   223: aload_0
    //   224: getfield 25	jw:jdField_a_of_type_Jt	Ljt;
    //   227: aload_2
    //   228: invokevirtual 94	jt:a	(Lli;)V
    //   231: aload 5
    //   233: monitorexit
    //   234: goto -149 -> 85
    //   237: astore_1
    //   238: aload_2
    //   239: astore_3
    //   240: aload_2
    //   241: astore 4
    //   243: aload 5
    //   245: monitorexit
    //   246: aload_2
    //   247: astore_3
    //   248: aload_2
    //   249: astore 4
    //   251: aload_1
    //   252: athrow
    //   253: astore_1
    //   254: aload_0
    //   255: getfield 31	jw:jdField_a_of_type_Kk	Lkk;
    //   258: sipush 804
    //   261: aconst_null
    //   262: aload_1
    //   263: invokevirtual 97	kk:a	(I[Ljava/lang/Object;Ljava/lang/Throwable;)V
    //   266: aload 4
    //   268: ifnull +20 -> 288
    //   271: aload 4
    //   273: instanceof 83
    //   276: ifeq +12 -> 288
    //   279: aload_0
    //   280: getfield 25	jw:jdField_a_of_type_Jt	Ljt;
    //   283: aload 4
    //   285: invokevirtual 94	jt:a	(Lli;)V
    //   288: aload_0
    //   289: iconst_0
    //   290: putfield 21	jw:jdField_a_of_type_Boolean	Z
    //   293: aload_0
    //   294: getfield 27	jw:jdField_a_of_type_Js	Ljs;
    //   297: new 66	jm
    //   300: dup
    //   301: aload_1
    //   302: iconst_0
    //   303: invokespecial 100	jm:<init>	(Ljava/lang/Throwable;B)V
    //   306: invokevirtual 88	js:a	(Ljm;)V
    //   309: aload 4
    //   311: astore_1
    //   312: goto -310 -> 2
    //   315: aload_2
    //   316: astore_3
    //   317: aload_2
    //   318: astore 4
    //   320: aload_0
    //   321: getfield 23	jw:jdField_a_of_type_JavaLangObject	Ljava/lang/Object;
    //   324: astore 5
    //   326: aload_2
    //   327: astore_3
    //   328: aload_2
    //   329: astore 4
    //   331: aload 5
    //   333: monitorenter
    //   334: aload_0
    //   335: iconst_0
    //   336: putfield 21	jw:jdField_a_of_type_Boolean	Z
    //   339: aload 5
    //   341: monitorexit
    //   342: aload_2
    //   343: astore_1
    //   344: goto -342 -> 2
    //   347: astore_1
    //   348: aload_2
    //   349: astore_3
    //   350: aload_2
    //   351: astore 4
    //   353: aload 5
    //   355: monitorexit
    //   356: aload_2
    //   357: astore_3
    //   358: aload_2
    //   359: astore 4
    //   361: aload_1
    //   362: athrow
    //   363: astore_2
    //   364: aload_1
    //   365: monitorexit
    //   366: aload_2
    //   367: athrow
    //   368: aload_0
    //   369: getfield 23	jw:jdField_a_of_type_JavaLangObject	Ljava/lang/Object;
    //   372: astore_2
    //   373: aload_2
    //   374: monitorenter
    //   375: aload_0
    //   376: getfield 31	jw:jdField_a_of_type_Kk	Lkk;
    //   379: sipush 805
    //   382: invokevirtual 59	kk:a	(I)V
    //   385: aload_0
    //   386: getfield 23	jw:jdField_a_of_type_JavaLangObject	Ljava/lang/Object;
    //   389: invokevirtual 103	java/lang/Object:notifyAll	()V
    //   392: aload_2
    //   393: monitorexit
    //   394: return
    //   395: astore_1
    //   396: aload_2
    //   397: monitorexit
    //   398: aload_1
    //   399: athrow
    // Local variable table:
    //   start	length	slot	name	signature
    //   0	400	0	this	jw
    //   1	137	1	localObject1	Object
    //   141	15	1	localObject2	Object
    //   162	20	1	localObject3	Object
    //   237	15	1	localObject4	Object
    //   253	49	1	localException	Exception
    //   311	33	1	localObject5	Object
    //   347	18	1	localObject6	Object
    //   395	4	1	localObject7	Object
    //   43	110	2	localli	li
    //   157	202	2	localjm	jm
    //   363	4	2	localObject8	Object
    //   17	341	3	localObject10	Object
    //   19	341	4	localObject11	Object
    //   108	246	5	localObject12	Object
    // Exception table:
    //   from	to	target	type
    //   118	136	141	finally
    //   21	31	157	jm
    //   36	44	157	jm
    //   53	60	157	jm
    //   65	73	157	jm
    //   78	85	157	jm
    //   92	99	157	jm
    //   104	110	157	jm
    //   115	118	157	jm
    //   147	150	157	jm
    //   155	157	157	jm
    //   190	200	157	jm
    //   205	208	157	jm
    //   243	246	157	jm
    //   251	253	157	jm
    //   320	326	157	jm
    //   331	334	157	jm
    //   353	356	157	jm
    //   361	363	157	jm
    //   208	234	237	finally
    //   21	31	253	java/lang/Exception
    //   36	44	253	java/lang/Exception
    //   53	60	253	java/lang/Exception
    //   65	73	253	java/lang/Exception
    //   78	85	253	java/lang/Exception
    //   92	99	253	java/lang/Exception
    //   104	110	253	java/lang/Exception
    //   115	118	253	java/lang/Exception
    //   147	150	253	java/lang/Exception
    //   155	157	253	java/lang/Exception
    //   190	200	253	java/lang/Exception
    //   205	208	253	java/lang/Exception
    //   243	246	253	java/lang/Exception
    //   251	253	253	java/lang/Exception
    //   320	326	253	java/lang/Exception
    //   331	334	253	java/lang/Exception
    //   353	356	253	java/lang/Exception
    //   361	363	253	java/lang/Exception
    //   334	342	347	finally
    //   165	172	363	finally
    //   375	394	395	finally
  }
}


/* Location:              E:\soft\ApkIDE\Worksrc\com.MobileTicket\!\jw.class
 * Java compiler version: 6 (50.0)
 * JD-Core Version:       0.7.1
 */