package com.worklight.androidgap.plugin;

 enum AnalyticsConfigurator$ACTIONS$1
{
  AnalyticsConfigurator$ACTIONS$1()
  {
    super(paramString, paramInt, null);
  }
  
  /* Error */
  public void doAction(AnalyticsConfigurator paramAnalyticsConfigurator, String arg2)
    throws org.json.JSONException
  {
    // Byte code:
    //   0: aconst_null
    //   1: astore 5
    //   3: new 29	org/json/JSONObject
    //   6: astore 7
    //   8: aload 7
    //   10: aload_2
    //   11: invokespecial 32	org/json/JSONObject:<init>	(Ljava/lang/String;)V
    //   14: new 29	org/json/JSONObject
    //   17: astore 8
    //   19: aload 8
    //   21: getstatic 36	com/worklight/androidgap/plugin/AnalyticsConfigurator:prefs	Landroid/content/SharedPreferences;
    //   24: getstatic 42	com/worklight/androidgap/plugin/AnalyticsConfigurator$OPTIONS:TEALEAF_PROPS	Lcom/worklight/androidgap/plugin/AnalyticsConfigurator$OPTIONS;
    //   27: invokevirtual 46	com/worklight/androidgap/plugin/AnalyticsConfigurator$OPTIONS:toString	()Ljava/lang/String;
    //   30: ldc 48
    //   32: invokeinterface 54 3 0
    //   37: invokespecial 32	org/json/JSONObject:<init>	(Ljava/lang/String;)V
    //   40: aload 8
    //   42: invokevirtual 58	org/json/JSONObject:keys	()Ljava/util/Iterator;
    //   45: astore 9
    //   47: aload 9
    //   49: monitorenter
    //   50: aload 9
    //   52: invokeinterface 64 1 0
    //   57: ifeq +83 -> 140
    //   60: aload 9
    //   62: invokeinterface 68 1 0
    //   67: checkcast 70	java/lang/String
    //   70: astore 10
    //   72: aconst_null
    //   73: astore_2
    //   74: aload 7
    //   76: aload 10
    //   78: invokevirtual 74	org/json/JSONObject:get	(Ljava/lang/String;)Ljava/lang/Object;
    //   81: checkcast 70	java/lang/String
    //   84: astore 6
    //   86: aload 6
    //   88: astore_2
    //   89: aload_2
    //   90: ifnull -40 -> 50
    //   93: aload_2
    //   94: aload 8
    //   96: aload 10
    //   98: invokevirtual 74	org/json/JSONObject:get	(Ljava/lang/String;)Ljava/lang/Object;
    //   101: invokevirtual 78	java/lang/String:equals	(Ljava/lang/Object;)Z
    //   104: ifeq -54 -> 50
    //   107: aload 7
    //   109: aload 10
    //   111: invokevirtual 81	org/json/JSONObject:remove	(Ljava/lang/String;)Ljava/lang/Object;
    //   114: pop
    //   115: goto -65 -> 50
    //   118: astore_1
    //   119: aload 9
    //   121: monitorexit
    //   122: aload_1
    //   123: athrow
    //   124: astore_2
    //   125: aload_2
    //   126: ifnull +13 -> 139
    //   129: invokestatic 84	com/worklight/androidgap/plugin/AnalyticsConfigurator:access$100	()Ljava/lang/String;
    //   132: ldc 86
    //   134: aload_2
    //   135: invokestatic 92	android/util/Log:w	(Ljava/lang/String;Ljava/lang/String;Ljava/lang/Throwable;)I
    //   138: pop
    //   139: return
    //   140: aload 9
    //   142: monitorexit
    //   143: aload 7
    //   145: invokevirtual 96	org/json/JSONObject:length	()I
    //   148: istore_3
    //   149: iload_3
    //   150: ifeq -11 -> 139
    //   153: getstatic 100	com/worklight/androidgap/plugin/AnalyticsConfigurator$ACTIONS$1:disable	Lcom/worklight/androidgap/plugin/AnalyticsConfigurator$ACTIONS;
    //   156: invokevirtual 101	com/worklight/androidgap/plugin/AnalyticsConfigurator$ACTIONS:toString	()Ljava/lang/String;
    //   159: invokestatic 105	com/worklight/androidgap/plugin/AnalyticsConfigurator$ACTIONS:fromString	(Ljava/lang/String;)Lcom/worklight/androidgap/plugin/AnalyticsConfigurator$ACTIONS;
    //   162: aload_1
    //   163: aconst_null
    //   164: invokevirtual 107	com/worklight/androidgap/plugin/AnalyticsConfigurator$ACTIONS:doAction	(Lcom/worklight/androidgap/plugin/AnalyticsConfigurator;Ljava/lang/String;)V
    //   167: ldc 109
    //   169: invokestatic 115	java/lang/Class:forName	(Ljava/lang/String;)Ljava/lang/Class;
    //   172: ldc 117
    //   174: iconst_2
    //   175: anewarray 111	java/lang/Class
    //   178: dup
    //   179: iconst_0
    //   180: ldc 70
    //   182: aastore
    //   183: dup
    //   184: iconst_1
    //   185: ldc 70
    //   187: aastore
    //   188: invokevirtual 121	java/lang/Class:getMethod	(Ljava/lang/String;[Ljava/lang/Class;)Ljava/lang/reflect/Method;
    //   191: astore 10
    //   193: aload 7
    //   195: invokevirtual 58	org/json/JSONObject:keys	()Ljava/util/Iterator;
    //   198: astore_2
    //   199: aload_2
    //   200: monitorenter
    //   201: aload_2
    //   202: invokeinterface 64 1 0
    //   207: ifeq +69 -> 276
    //   210: aload_2
    //   211: invokeinterface 68 1 0
    //   216: checkcast 70	java/lang/String
    //   219: astore 6
    //   221: aload 7
    //   223: aload 6
    //   225: invokevirtual 74	org/json/JSONObject:get	(Ljava/lang/String;)Ljava/lang/Object;
    //   228: checkcast 70	java/lang/String
    //   231: astore 9
    //   233: aload 10
    //   235: aconst_null
    //   236: iconst_2
    //   237: anewarray 123	java/lang/Object
    //   240: dup
    //   241: iconst_0
    //   242: aload 6
    //   244: aastore
    //   245: dup
    //   246: iconst_1
    //   247: aload 9
    //   249: aastore
    //   250: invokevirtual 129	java/lang/reflect/Method:invoke	(Ljava/lang/Object;[Ljava/lang/Object;)Ljava/lang/Object;
    //   253: pop
    //   254: aload 8
    //   256: aload 6
    //   258: aload 9
    //   260: invokevirtual 133	org/json/JSONObject:put	(Ljava/lang/String;Ljava/lang/Object;)Lorg/json/JSONObject;
    //   263: pop
    //   264: goto -63 -> 201
    //   267: astore_1
    //   268: aload_2
    //   269: monitorexit
    //   270: aload_1
    //   271: athrow
    //   272: astore_2
    //   273: goto -148 -> 125
    //   276: aload_2
    //   277: monitorexit
    //   278: getstatic 36	com/worklight/androidgap/plugin/AnalyticsConfigurator:prefs	Landroid/content/SharedPreferences;
    //   281: invokeinterface 137 1 0
    //   286: getstatic 42	com/worklight/androidgap/plugin/AnalyticsConfigurator$OPTIONS:TEALEAF_PROPS	Lcom/worklight/androidgap/plugin/AnalyticsConfigurator$OPTIONS;
    //   289: invokevirtual 46	com/worklight/androidgap/plugin/AnalyticsConfigurator$OPTIONS:toString	()Ljava/lang/String;
    //   292: aload 8
    //   294: invokevirtual 138	org/json/JSONObject:toString	()Ljava/lang/String;
    //   297: invokeinterface 144 3 0
    //   302: invokeinterface 147 1 0
    //   307: pop
    //   308: getstatic 36	com/worklight/androidgap/plugin/AnalyticsConfigurator:prefs	Landroid/content/SharedPreferences;
    //   311: getstatic 150	com/worklight/androidgap/plugin/AnalyticsConfigurator$OPTIONS:ENABLED	Lcom/worklight/androidgap/plugin/AnalyticsConfigurator$OPTIONS;
    //   314: invokevirtual 46	com/worklight/androidgap/plugin/AnalyticsConfigurator$OPTIONS:toString	()Ljava/lang/String;
    //   317: iconst_0
    //   318: invokeinterface 154 3 0
    //   323: istore 4
    //   325: aload 5
    //   327: astore_2
    //   328: iload 4
    //   330: ifeq -205 -> 125
    //   333: getstatic 157	com/worklight/androidgap/plugin/AnalyticsConfigurator$ACTIONS$1:enable	Lcom/worklight/androidgap/plugin/AnalyticsConfigurator$ACTIONS;
    //   336: invokevirtual 101	com/worklight/androidgap/plugin/AnalyticsConfigurator$ACTIONS:toString	()Ljava/lang/String;
    //   339: invokestatic 105	com/worklight/androidgap/plugin/AnalyticsConfigurator$ACTIONS:fromString	(Ljava/lang/String;)Lcom/worklight/androidgap/plugin/AnalyticsConfigurator$ACTIONS;
    //   342: aload_1
    //   343: aconst_null
    //   344: invokevirtual 107	com/worklight/androidgap/plugin/AnalyticsConfigurator$ACTIONS:doAction	(Lcom/worklight/androidgap/plugin/AnalyticsConfigurator;Ljava/lang/String;)V
    //   347: aload 5
    //   349: astore_2
    //   350: goto -225 -> 125
    //   353: astore_1
    //   354: aload 5
    //   356: astore_2
    //   357: goto -232 -> 125
    //   360: astore_2
    //   361: goto -236 -> 125
    //   364: astore_2
    //   365: goto -240 -> 125
    //   368: astore_2
    //   369: goto -202 -> 167
    //   372: astore 6
    //   374: goto -285 -> 89
    // Local variable table:
    //   start	length	slot	name	signature
    //   0	377	0	this	1
    //   0	377	1	paramAnalyticsConfigurator	AnalyticsConfigurator
    //   148	2	3	i	int
    //   323	6	4	bool	boolean
    //   1	354	5	localObject1	Object
    //   84	173	6	str	String
    //   372	1	6	localJSONException	org.json.JSONException
    //   6	216	7	localJSONObject1	org.json.JSONObject
    //   17	276	8	localJSONObject2	org.json.JSONObject
    //   70	164	10	localObject3	Object
    // Exception table:
    //   from	to	target	type
    //   50	72	118	finally
    //   74	86	118	finally
    //   93	115	118	finally
    //   119	122	118	finally
    //   140	143	118	finally
    //   3	50	124	java/lang/ClassNotFoundException
    //   122	124	124	java/lang/ClassNotFoundException
    //   143	149	124	java/lang/ClassNotFoundException
    //   153	167	124	java/lang/ClassNotFoundException
    //   167	201	124	java/lang/ClassNotFoundException
    //   270	272	124	java/lang/ClassNotFoundException
    //   278	325	124	java/lang/ClassNotFoundException
    //   333	347	124	java/lang/ClassNotFoundException
    //   201	264	267	finally
    //   268	270	267	finally
    //   276	278	267	finally
    //   3	50	272	java/lang/reflect/InvocationTargetException
    //   122	124	272	java/lang/reflect/InvocationTargetException
    //   143	149	272	java/lang/reflect/InvocationTargetException
    //   153	167	272	java/lang/reflect/InvocationTargetException
    //   167	201	272	java/lang/reflect/InvocationTargetException
    //   270	272	272	java/lang/reflect/InvocationTargetException
    //   278	325	272	java/lang/reflect/InvocationTargetException
    //   333	347	272	java/lang/reflect/InvocationTargetException
    //   333	347	353	java/net/MalformedURLException
    //   3	50	360	java/lang/NoSuchMethodException
    //   122	124	360	java/lang/NoSuchMethodException
    //   143	149	360	java/lang/NoSuchMethodException
    //   153	167	360	java/lang/NoSuchMethodException
    //   167	201	360	java/lang/NoSuchMethodException
    //   270	272	360	java/lang/NoSuchMethodException
    //   278	325	360	java/lang/NoSuchMethodException
    //   333	347	360	java/lang/NoSuchMethodException
    //   3	50	364	java/lang/IllegalAccessException
    //   122	124	364	java/lang/IllegalAccessException
    //   143	149	364	java/lang/IllegalAccessException
    //   153	167	364	java/lang/IllegalAccessException
    //   167	201	364	java/lang/IllegalAccessException
    //   270	272	364	java/lang/IllegalAccessException
    //   278	325	364	java/lang/IllegalAccessException
    //   333	347	364	java/lang/IllegalAccessException
    //   153	167	368	java/net/MalformedURLException
    //   74	86	372	org/json/JSONException
  }
}


/* Location:              E:\soft\ApkIDE\Worksrc\com.MobileTicket\!\com\worklight\androidgap\plugin\AnalyticsConfigurator$ACTIONS$1.class
 * Java compiler version: 6 (50.0)
 * JD-Core Version:       0.7.1
 */